[{"InstanceId":"1ed7ba6b23894dc6b02125d2e6f406c2","Name":"Rapid Jab","OwnerId":30,"Owner":"MetaKnight","HitboxActive":"4, 7, 10, 13, 16, 19, 22","FirstActionableFrame":"-","BaseDamage":"1","Angle":"361","BaseKnockBackSetKnockback":"10","LandingLag":null,"AutoCancel":null,"KnockbackGrowth":"30","MoveType":"ground","IsWeightDependent":false,"Game":"Ultimate","Related":{"Smash4":{"Character":"http://api.kuroganehammer.com/api/characters/name/MetaKnight?game=smash4"},"Ultimate":{"Character":"http://api.kuroganehammer.com/api/characters/name/MetaKnight?game=ultimate","Self":"http://api.kuroganehammer.com/api/moves/1ed7ba6b23894dc6b02125d2e6f406c2?game=ultimate"}},"Links":[{"Rel":"self","Href":"http://api.kuroganehammer.com/api/moves/1ed7ba6b23894dc6b02125d2e6f406c2?game=ultimate"},{"Rel":"character","Href":"http://api.kuroganehammer.com/api/characters/name/MetaKnight?game=ultimate"}]},{"InstanceId":"8a1fdb45edf143ad9546ccfdd923f491","Name":"Rapid Jab Finisher","OwnerId":30,"Owner":"MetaKnight","HitboxActive":"3","FirstActionableFrame":"31","BaseDamage":"2","Angle":"361","BaseKnockBackSetKnockback":"60","LandingLag":null,"AutoCancel":null,"KnockbackGrowth":"140","MoveType":"ground","IsWeightDependent":false,"Game":"Ultimate","Related":{"Smash4":{"Character":"http://api.kuroganehammer.com/api/characters/name/MetaKnight?game=smash4"},"Ultimate":{"Character":"http://api.kuroganehammer.com/api/characters/name/MetaKnight?game=ultimate","Self":"http://api.kuroganehammer.com/api/moves/8a1fdb45edf143ad9546ccfdd923f491?game=ultimate"}},"Links":[{"Rel":"self","Href":"http://api.kuroganehammer.com/api/moves/8a1fdb45edf143ad9546ccfdd923f491?game=ultimate"},{"Rel":"character","Href":"http://api.kuroganehammer.com/api/characters/name/MetaKnight?game=ultimate"}]},{"InstanceId":"7af3e6d0f9d8412eacf52e1e49fb3d57","Name":"Dash Attack","OwnerId":30,"Owner":"MetaKnight","HitboxActive":"7-11","FirstActionableFrame":"33","BaseDamage":"7/7/6","Angle":"60/70/80","BaseKnockBackSetKnockback":"65/65/67","LandingLag":null,"AutoCancel":null,"KnockbackGrowth":"107","MoveType":"ground","IsWeightDependent":false,"Game":"Ultimate","Related":{"Smash4":{"Character":"http://api.kuroganehammer.com/api/characters/name/MetaKnight?game=smash4"},"Ultimate":{"Character":"http://api.kuroganehammer.com/api/characters/name/MetaKnight?game=ultimate","Self":"http://api.kuroganehammer.com/api/moves/7af3e6d0f9d8412eacf52e1e49fb3d57?game=ultimate"}},"Links":[{"Rel":"self","Href":"http://api.kuroganehammer.com/api/moves/7af3e6d0f9d8412eacf52e1e49fb3d57?game=ultimate"},{"Rel":"character","Href":"http://api.kuroganehammer.com/api/characters/name/MetaKnight?game=ultimate"}]},{"InstanceId":"deeade1494684bef96683a080f7dd110","Name":"Ftilt 1","OwnerId":30,"Owner":"MetaKnight","HitboxActive":"6","FirstActionableFrame":"26","BaseDamage":"2","Angle":"68/88","BaseKnockBackSetKnockback":"25","LandingLag":null,"AutoCancel":null,"KnockbackGrowth":"20","MoveType":"ground","IsWeightDependent":false,"Game":"Ultimate","Related":{"Smash4":{"Character":"http://api.kuroganehammer.com/api/characters/name/MetaKnight?game=smash4"},"Ultimate":{"Character":"http://api.kuroganehammer.com/api/characters/name/MetaKnight?game=ultimate","Self":"http://api.kuroganehammer.com/api/moves/deeade1494684bef96683a080f7dd110?game=ultimate"}},"Links":[{"Rel":"self","Href":"http://api.kuroganehammer.com/api/moves/deeade1494684bef96683a080f7dd110?game=ultimate"},{"Rel":"character","Href":"http://api.kuroganehammer.com/api/characters/name/MetaKnight?game=ultimate"}]},{"InstanceId":"2e7b65d0567a490ba4f5365a086e61f8","Name":"Ftilt 2","OwnerId":30,"Owner":"MetaKnight","HitboxActive":"2","FirstActionableFrame":"28","BaseDamage":"2","Angle":"60/85","BaseKnockBackSetKnockback":"20","LandingLag":null,"AutoCancel":null,"KnockbackGrowth":"20","MoveType":"ground","IsWeightDependent":false,"Game":"Ultimate","Related":{"Smash4":{"Character":"http://api.kuroganehammer.com/api/characters/name/MetaKnight?game=smash4"},"Ultimate":{"Character":"http://api.kuroganehammer.com/api/characters/name/MetaKnight?game=ultimate","Self":"http://api.kuroganehammer.com/api/moves/2e7b65d0567a490ba4f5365a086e61f8?game=ultimate"}},"Links":[{"Rel":"self","Href":"http://api.kuroganehammer.com/api/moves/2e7b65d0567a490ba4f5365a086e61f8?game=ultimate"},{"Rel":"character","Href":"http://api.kuroganehammer.com/api/characters/name/MetaKnight?game=ultimate"}]},{"InstanceId":"ca1ee94cab9e4e4db961f917b39d6386","Name":"Ftilt 3","OwnerId":30,"Owner":"MetaKnight","HitboxActive":"2","FirstActionableFrame":"31","BaseDamage":"4","Angle":"361","BaseKnockBackSetKnockback":"80","LandingLag":null,"AutoCancel":null,"KnockbackGrowth":"107","MoveType":"ground","IsWeightDependent":false,"Game":"Ultimate","Related":{"Smash4":{"Character":"http://api.kuroganehammer.com/api/characters/name/MetaKnight?game=smash4"},"Ultimate":{"Character":"http://api.kuroganehammer.com/api/characters/name/MetaKnight?game=ultimate","Self":"http://api.kuroganehammer.com/api/moves/ca1ee94cab9e4e4db961f917b39d6386?game=ultimate"}},"Links":[{"Rel":"self","Href":"http://api.kuroganehammer.com/api/moves/ca1ee94cab9e4e4db961f917b39d6386?game=ultimate"},{"Rel":"character","Href":"http://api.kuroganehammer.com/api/characters/name/MetaKnight?game=ultimate"}]},{"InstanceId":"0dfbe99e86364ca484bd112e920063a6","Name":"Utilt","OwnerId":30,"Owner":"MetaKnight","HitboxActive":"8-10","FirstActionableFrame":"35","BaseDamage":"7/6","Angle":"95","BaseKnockBackSetKnockback":"60","LandingLag":null,"AutoCancel":null,"KnockbackGrowth":"90","MoveType":"ground","IsWeightDependent":false,"Game":"Ultimate","Related":{"Smash4":{"Character":"http://api.kuroganehammer.com/api/characters/name/MetaKnight?game=smash4"},"Ultimate":{"Character":"http://api.kuroganehammer.com/api/characters/name/MetaKnight?game=ultimate","Self":"http://api.kuroganehammer.com/api/moves/0dfbe99e86364ca484bd112e920063a6?game=ultimate"}},"Links":[{"Rel":"self","Href":"http://api.kuroganehammer.com/api/moves/0dfbe99e86364ca484bd112e920063a6?game=ultimate"},{"Rel":"character","Href":"http://api.kuroganehammer.com/api/characters/name/MetaKnight?game=ultimate"}]},{"InstanceId":"7921cc5007e242b3ab79dd41f06abb7d","Name":"Utilt (Late)","OwnerId":30,"Owner":"MetaKnight","HitboxActive":"11-14","FirstActionableFrame":"-","BaseDamage":"7/5","Angle":"95/85","BaseKnockBackSetKnockback":"60/35","LandingLag":null,"AutoCancel":null,"KnockbackGrowth":"90/120","MoveType":"ground","IsWeightDependent":false,"Game":"Ultimate","Related":{"Smash4":{"Character":"http://api.kuroganehammer.com/api/characters/name/MetaKnight?game=smash4"},"Ultimate":{"Character":"http://api.kuroganehammer.com/api/characters/name/MetaKnight?game=ultimate","Self":"http://api.kuroganehammer.com/api/moves/7921cc5007e242b3ab79dd41f06abb7d?game=ultimate"}},"Links":[{"Rel":"self","Href":"http://api.kuroganehammer.com/api/moves/7921cc5007e242b3ab79dd41f06abb7d?game=ultimate"},{"Rel":"character","Href":"http://api.kuroganehammer.com/api/characters/name/MetaKnight?game=ultimate"}]},{"InstanceId":"cec21fdb91d941f8a5709724f4f1b110","Name":"Dtilt","OwnerId":30,"Owner":"MetaKnight","HitboxActive":"3","FirstActionableFrame":"19","BaseDamage":"5","Angle":"361","BaseKnockBackSetKnockback":"15","LandingLag":null,"AutoCancel":null,"KnockbackGrowth":"88","MoveType":"ground","IsWeightDependent":false,"Game":"Ultimate","Related":{"Smash4":{"Character":"http://api.kuroganehammer.com/api/characters/name/MetaKnight?game=smash4"},"Ultimate":{"Character":"http://api.kuroganehammer.com/api/characters/name/MetaKnight?game=ultimate","Self":"http://api.kuroganehammer.com/api/moves/cec21fdb91d941f8a5709724f4f1b110?game=ultimate"}},"Links":[{"Rel":"self","Href":"http://api.kuroganehammer.com/api/moves/cec21fdb91d941f8a5709724f4f1b110?game=ultimate"},{"Rel":"character","Href":"http://api.kuroganehammer.com/api/characters/name/MetaKnight?game=ultimate"}]},{"InstanceId":"4378d08f26f2493e8c3c1eb36a9ed13f","Name":"Fsmash","OwnerId":30,"Owner":"MetaKnight","HitboxActive":"24","FirstActionableFrame":"42","BaseDamage":"16","Angle":"361","BaseKnockBackSetKnockback":"30","LandingLag":null,"AutoCancel":null,"KnockbackGrowth":"108/98","MoveType":"ground","IsWeightDependent":false,"Game":"Ultimate","Related":{"Smash4":{"Character":"http://api.kuroganehammer.com/api/characters/name/MetaKnight?game=smash4"},"Ultimate":{"Character":"http://api.kuroganehammer.com/api/characters/name/MetaKnight?game=ultimate","Self":"http://api.kuroganehammer.com/api/moves/4378d08f26f2493e8c3c1eb36a9ed13f?game=ultimate"}},"Links":[{"Rel":"self","Href":"http://api.kuroganehammer.com/api/moves/4378d08f26f2493e8c3c1eb36a9ed13f?game=ultimate"},{"Rel":"character","Href":"http://api.kuroganehammer.com/api/characters/name/MetaKnight?game=ultimate"}]},{"InstanceId":"51d7153594aa4bd1bbb7c4210a43310c","Name":"Usmash (Hit 1)","OwnerId":30,"Owner":"MetaKnight","HitboxActive":"8","FirstActionableFrame":"50","BaseDamage":"4","Angle":"366/130/130","BaseKnockBackSetKnockback":"F: 30 B: 30","LandingLag":null,"AutoCancel":null,"KnockbackGrowth":"100","MoveType":"ground","IsWeightDependent":false,"Game":"Ultimate","Related":{"Smash4":{"Character":"http://api.kuroganehammer.com/api/characters/name/MetaKnight?game=smash4"},"Ultimate":{"Character":"http://api.kuroganehammer.com/api/characters/name/MetaKnight?game=ultimate","Self":"http://api.kuroganehammer.com/api/moves/51d7153594aa4bd1bbb7c4210a43310c?game=ultimate"}},"Links":[{"Rel":"self","Href":"http://api.kuroganehammer.com/api/moves/51d7153594aa4bd1bbb7c4210a43310c?game=ultimate"},{"Rel":"character","Href":"http://api.kuroganehammer.com/api/characters/name/MetaKnight?game=ultimate"}]},{"InstanceId":"06edfd67042042b5b659ce9483ecb0d9","Name":"Usmash (Hit 2)","OwnerId":30,"Owner":"MetaKnight","HitboxActive":"12","FirstActionableFrame":"-","BaseDamage":"3","Angle":"366/130/130","BaseKnockBackSetKnockback":"F: 30 B: 30","LandingLag":null,"AutoCancel":null,"KnockbackGrowth":"100","MoveType":"ground","IsWeightDependent":false,"Game":"Ultimate","Related":{"Smash4":{"Character":"http://api.kuroganehammer.com/api/characters/name/MetaKnight?game=smash4"},"Ultimate":{"Character":"http://api.kuroganehammer.com/api/characters/name/MetaKnight?game=ultimate","Self":"http://api.kuroganehammer.com/api/moves/06edfd67042042b5b659ce9483ecb0d9?game=ultimate"}},"Links":[{"Rel":"self","Href":"http://api.kuroganehammer.com/api/moves/06edfd67042042b5b659ce9483ecb0d9?game=ultimate"},{"Rel":"character","Href":"http://api.kuroganehammer.com/api/characters/name/MetaKnight?game=ultimate"}]},{"InstanceId":"247acd845bc54402a440d8ecd44b9320","Name":"Usmash (Hit 3)","OwnerId":30,"Owner":"MetaKnight","HitboxActive":"17","FirstActionableFrame":"-","BaseDamage":"5","Angle":"85/85/90","BaseKnockBackSetKnockback":"65","LandingLag":null,"AutoCancel":null,"KnockbackGrowth":"148","MoveType":"ground","IsWeightDependent":false,"Game":"Ultimate","Related":{"Smash4":{"Character":"http://api.kuroganehammer.com/api/characters/name/MetaKnight?game=smash4"},"Ultimate":{"Character":"http://api.kuroganehammer.com/api/characters/name/MetaKnight?game=ultimate","Self":"http://api.kuroganehammer.com/api/moves/247acd845bc54402a440d8ecd44b9320?game=ultimate"}},"Links":[{"Rel":"self","Href":"http://api.kuroganehammer.com/api/moves/247acd845bc54402a440d8ecd44b9320?game=ultimate"},{"Rel":"character","Href":"http://api.kuroganehammer.com/api/characters/name/MetaKnight?game=ultimate"}]},{"InstanceId":"9d09d5e16730489db3833edd9cf8c805","Name":"Dsmash (Hit 1)","OwnerId":30,"Owner":"MetaKnight","HitboxActive":"4","FirstActionableFrame":"38","BaseDamage":"10","Angle":"35","BaseKnockBackSetKnockback":"50","LandingLag":null,"AutoCancel":null,"KnockbackGrowth":"77","MoveType":"ground","IsWeightDependent":false,"Game":"Ultimate","Related":{"Smash4":{"Character":"http://api.kuroganehammer.com/api/characters/name/MetaKnight?game=smash4"},"Ultimate":{"Character":"http://api.kuroganehammer.com/api/characters/name/MetaKnight?game=ultimate","Self":"http://api.kuroganehammer.com/api/moves/9d09d5e16730489db3833edd9cf8c805?game=ultimate"}},"Links":[{"Rel":"self","Href":"http://api.kuroganehammer.com/api/moves/9d09d5e16730489db3833edd9cf8c805?game=ultimate"},{"Rel":"character","Href":"http://api.kuroganehammer.com/api/characters/name/MetaKnight?game=ultimate"}]},{"InstanceId":"528d7886e3004ceeb32fe4136e183f26","Name":"Dsmash (Hit 2)","OwnerId":30,"Owner":"MetaKnight","HitboxActive":"9","FirstActionableFrame":"-","BaseDamage":"13","Angle":"35","BaseKnockBackSetKnockback":"50","LandingLag":null,"AutoCancel":null,"KnockbackGrowth":"78","MoveType":"ground","IsWeightDependent":false,"Game":"Ultimate","Related":{"Smash4":{"Character":"http://api.kuroganehammer.com/api/characters/name/MetaKnight?game=smash4"},"Ultimate":{"Character":"http://api.kuroganehammer.com/api/characters/name/MetaKnight?game=ultimate","Self":"http://api.kuroganehammer.com/api/moves/528d7886e3004ceeb32fe4136e183f26?game=ultimate"}},"Links":[{"Rel":"self","Href":"http://api.kuroganehammer.com/api/moves/528d7886e3004ceeb32fe4136e183f26?game=ultimate"},{"Rel":"character","Href":"http://api.kuroganehammer.com/api/characters/name/MetaKnight?game=ultimate"}]},{"InstanceId":"73b76cbfe7f34d26a575a11d01ef4c51","Name":"Standing Grab","OwnerId":30,"Owner":"MetaKnight","HitboxActive":"7-8","FirstActionableFrame":"37","BaseDamage":"","Angle":"","BaseKnockBackSetKnockback":"","LandingLag":null,"AutoCancel":null,"KnockbackGrowth":"","MoveType":"ground","IsWeightDependent":false,"Game":"Ultimate","Related":{"Smash4":{"Character":"http://api.kuroganehammer.com/api/characters/name/MetaKnight?game=smash4"},"Ultimate":{"Character":"http://api.kuroganehammer.com/api/characters/name/MetaKnight?game=ultimate","Self":"http://api.kuroganehammer.com/api/moves/73b76cbfe7f34d26a575a11d01ef4c51?game=ultimate"}},"Links":[{"Rel":"self","Href":"http://api.kuroganehammer.com/api/moves/73b76cbfe7f34d26a575a11d01ef4c51?game=ultimate"},{"Rel":"character","Href":"http://api.kuroganehammer.com/api/characters/name/MetaKnight?game=ultimate"}]},{"InstanceId":"160b21eb18d7436592576b6e1608b9e0","Name":"Dash Grab","OwnerId":30,"Owner":"MetaKnight","HitboxActive":"11-12","FirstActionableFrame":"45","BaseDamage":"","Angle":"","BaseKnockBackSetKnockback":"","LandingLag":null,"AutoCancel":null,"KnockbackGrowth":"","MoveType":"ground","IsWeightDependent":false,"Game":"Ultimate","Related":{"Smash4":{"Character":"http://api.kuroganehammer.com/api/characters/name/MetaKnight?game=smash4"},"Ultimate":{"Character":"http://api.kuroganehammer.com/api/characters/name/MetaKnight?game=ultimate","Self":"http://api.kuroganehammer.com/api/moves/160b21eb18d7436592576b6e1608b9e0?game=ultimate"}},"Links":[{"Rel":"self","Href":"http://api.kuroganehammer.com/api/moves/160b21eb18d7436592576b6e1608b9e0?game=ultimate"},{"Rel":"character","Href":"http://api.kuroganehammer.com/api/characters/name/MetaKnight?game=ultimate"}]},{"InstanceId":"0aecefe91c9845668f64d776a93279aa","Name":"Pivot Grab","OwnerId":30,"Owner":"MetaKnight","HitboxActive":"12-13","FirstActionableFrame":"40","BaseDamage":"","Angle":"","BaseKnockBackSetKnockback":"","LandingLag":null,"AutoCancel":null,"KnockbackGrowth":"","MoveType":"ground","IsWeightDependent":false,"Game":"Ultimate","Related":{"Smash4":{"Character":"http://api.kuroganehammer.com/api/characters/name/MetaKnight?game=smash4"},"Ultimate":{"Character":"http://api.kuroganehammer.com/api/characters/name/MetaKnight?game=ultimate","Self":"http://api.kuroganehammer.com/api/moves/0aecefe91c9845668f64d776a93279aa?game=ultimate"}},"Links":[{"Rel":"self","Href":"http://api.kuroganehammer.com/api/moves/0aecefe91c9845668f64d776a93279aa?game=ultimate"},{"Rel":"character","Href":"http://api.kuroganehammer.com/api/characters/name/MetaKnight?game=ultimate"}]},{"InstanceId":"7a4a8664a82f457180ed8bbdd89fc934","Name":"Spotdodge","OwnerId":30,"Owner":"MetaKnight","HitboxActive":"3-16","FirstActionableFrame":"25","BaseDamage":"","Angle":"","BaseKnockBackSetKnockback":"","LandingLag":null,"AutoCancel":null,"KnockbackGrowth":"","MoveType":"ground","IsWeightDependent":false,"Game":"Ultimate","Related":{"Smash4":{"Character":"http://api.kuroganehammer.com/api/characters/name/MetaKnight?game=smash4"},"Ultimate":{"Character":"http://api.kuroganehammer.com/api/characters/name/MetaKnight?game=ultimate","Self":"http://api.kuroganehammer.com/api/moves/7a4a8664a82f457180ed8bbdd89fc934?game=ultimate"}},"Links":[{"Rel":"self","Href":"http://api.kuroganehammer.com/api/moves/7a4a8664a82f457180ed8bbdd89fc934?game=ultimate"},{"Rel":"character","Href":"http://api.kuroganehammer.com/api/characters/name/MetaKnight?game=ultimate"}]},{"InstanceId":"4705513df6b04ba785f96eb0406ea167","Name":"Forward Roll","OwnerId":30,"Owner":"MetaKnight","HitboxActive":"4-14","FirstActionableFrame":"29","BaseDamage":"","Angle":"","BaseKnockBackSetKnockback":"","LandingLag":null,"AutoCancel":null,"KnockbackGrowth":"","MoveType":"ground","IsWeightDependent":false,"Game":"Ultimate","Related":{"Smash4":{"Character":"http://api.kuroganehammer.com/api/characters/name/MetaKnight?game=smash4"},"Ultimate":{"Character":"http://api.kuroganehammer.com/api/characters/name/MetaKnight?game=ultimate","Self":"http://api.kuroganehammer.com/api/moves/4705513df6b04ba785f96eb0406ea167?game=ultimate"}},"Links":[{"Rel":"self","Href":"http://api.kuroganehammer.com/api/moves/4705513df6b04ba785f96eb0406ea167?game=ultimate"},{"Rel":"character","Href":"http://api.kuroganehammer.com/api/characters/name/MetaKnight?game=ultimate"}]},{"InstanceId":"99c3aa8b8d8946e2b43849b837eedfeb","Name":"Back Roll","OwnerId":30,"Owner":"MetaKnight","HitboxActive":"4-15","FirstActionableFrame":"34","BaseDamage":"","Angle":"","BaseKnockBackSetKnockback":"","LandingLag":null,"AutoCancel":null,"KnockbackGrowth":"","MoveType":"ground","IsWeightDependent":false,"Game":"Ultimate","Related":{"Smash4":{"Character":"http://api.kuroganehammer.com/api/characters/name/MetaKnight?game=smash4"},"Ultimate":{"Character":"http://api.kuroganehammer.com/api/characters/name/MetaKnight?game=ultimate","Self":"http://api.kuroganehammer.com/api/moves/99c3aa8b8d8946e2b43849b837eedfeb?game=ultimate"}},"Links":[{"Rel":"self","Href":"http://api.kuroganehammer.com/api/moves/99c3aa8b8d8946e2b43849b837eedfeb?game=ultimate"},{"Rel":"character","Href":"http://api.kuroganehammer.com/api/characters/name/MetaKnight?game=ultimate"}]},{"InstanceId":"332b4ddbf87346678e8bee7e76cd5077","Name":"Airdodge","OwnerId":30,"Owner":"MetaKnight","HitboxActive":"2-26","FirstActionableFrame":"48","BaseDamage":"","Angle":"","BaseKnockBackSetKnockback":"","LandingLag":null,"AutoCancel":null,"KnockbackGrowth":"","MoveType":"ground","IsWeightDependent":false,"Game":"Ultimate","Related":{"Smash4":{"Character":"http://api.kuroganehammer.com/api/characters/name/MetaKnight?game=smash4"},"Ultimate":{"Character":"http://api.kuroganehammer.com/api/characters/name/MetaKnight?game=ultimate","Self":"http://api.kuroganehammer.com/api/moves/332b4ddbf87346678e8bee7e76cd5077?game=ultimate"}},"Links":[{"Rel":"self","Href":"http://api.kuroganehammer.com/api/moves/332b4ddbf87346678e8bee7e76cd5077?game=ultimate"},{"Rel":"character","Href":"http://api.kuroganehammer.com/api/characters/name/MetaKnight?game=ultimate"}]},{"InstanceId":"bb8a0e7a1a8942eabaae69de123bd172","Name":"Directional Airdodge (F/B)","OwnerId":30,"Owner":"MetaKnight","HitboxActive":"2-19","FirstActionableFrame":"81","BaseDamage":"","Angle":"","BaseKnockBackSetKnockback":"","LandingLag":null,"AutoCancel":null,"KnockbackGrowth":"","MoveType":"ground","IsWeightDependent":false,"Game":"Ultimate","Related":{"Smash4":{"Character":"http://api.kuroganehammer.com/api/characters/name/MetaKnight?game=smash4"},"Ultimate":{"Character":"http://api.kuroganehammer.com/api/characters/name/MetaKnight?game=ultimate","Self":"http://api.kuroganehammer.com/api/moves/bb8a0e7a1a8942eabaae69de123bd172?game=ultimate"}},"Links":[{"Rel":"self","Href":"http://api.kuroganehammer.com/api/moves/bb8a0e7a1a8942eabaae69de123bd172?game=ultimate"},{"Rel":"character","Href":"http://api.kuroganehammer.com/api/characters/name/MetaKnight?game=ultimate"}]},{"InstanceId":"353b6c19a99b4d6dba10ef5748c93873","Name":"Directional Airdodge (U)","OwnerId":30,"Owner":"MetaKnight","HitboxActive":"2-19","FirstActionableFrame":"102","BaseDamage":"","Angle":"","BaseKnockBackSetKnockback":"","LandingLag":null,"AutoCancel":null,"KnockbackGrowth":"","MoveType":"ground","IsWeightDependent":false,"Game":"Ultimate","Related":{"Smash4":{"Character":"http://api.kuroganehammer.com/api/characters/name/MetaKnight?game=smash4"},"Ultimate":{"Character":"http://api.kuroganehammer.com/api/characters/name/MetaKnight?game=ultimate","Self":"http://api.kuroganehammer.com/api/moves/353b6c19a99b4d6dba10ef5748c93873?game=ultimate"}},"Links":[{"Rel":"self","Href":"http://api.kuroganehammer.com/api/moves/353b6c19a99b4d6dba10ef5748c93873?game=ultimate"},{"Rel":"character","Href":"http://api.kuroganehammer.com/api/characters/name/MetaKnight?game=ultimate"}]},{"InstanceId":"ceaf26d0875d4c888f18292bfa8272fb","Name":"Directional Airdodge (D)","OwnerId":30,"Owner":"MetaKnight","HitboxActive":"2-19","FirstActionableFrame":"67","BaseDamage":"","Angle":"","BaseKnockBackSetKnockback":"","LandingLag":null,"AutoCancel":null,"KnockbackGrowth":"","MoveType":"ground","IsWeightDependent":false,"Game":"Ultimate","Related":{"Smash4":{"Character":"http://api.kuroganehammer.com/api/characters/name/MetaKnight?game=smash4"},"Ultimate":{"Character":"http://api.kuroganehammer.com/api/characters/name/MetaKnight?game=ultimate","Self":"http://api.kuroganehammer.com/api/moves/ceaf26d0875d4c888f18292bfa8272fb?game=ultimate"}},"Links":[{"Rel":"self","Href":"http://api.kuroganehammer.com/api/moves/ceaf26d0875d4c888f18292bfa8272fb?game=ultimate"},{"Rel":"character","Href":"http://api.kuroganehammer.com/api/characters/name/MetaKnight?game=ultimate"}]},{"InstanceId":"bf2042838d544a5997b32aa25b593beb","Name":"Nair","OwnerId":30,"Owner":"MetaKnight","HitboxActive":"6-7","FirstActionableFrame":"44","BaseDamage":"10","Angle":"361","BaseKnockBackSetKnockback":"40","LandingLag":"7","AutoCancel":"1-5, 40>","KnockbackGrowth":"100","MoveType":"aerial","IsWeightDependent":false,"Game":"Ultimate","Related":{"Smash4":{"Character":"http://api.kuroganehammer.com/api/characters/name/MetaKnight?game=smash4"},"Ultimate":{"Character":"http://api.kuroganehammer.com/api/characters/name/MetaKnight?game=ultimate","Self":"http://api.kuroganehammer.com/api/moves/bf2042838d544a5997b32aa25b593beb?game=ultimate"}},"Links":[{"Rel":"self","Href":"http://api.kuroganehammer.com/api/moves/bf2042838d544a5997b32aa25b593beb?game=ultimate"},{"Rel":"character","Href":"http://api.kuroganehammer.com/api/characters/name/MetaKnight?game=ultimate"}]},{"InstanceId":"7a6c53bcfab644cbbf675b67c78aad45","Name":"Nair (Late)","OwnerId":30,"Owner":"MetaKnight","HitboxActive":"8-20","FirstActionableFrame":"-","BaseDamage":"7.5","Angle":"361","BaseKnockBackSetKnockback":"40","LandingLag":"-","AutoCancel":"-","KnockbackGrowth":"100","MoveType":"aerial","IsWeightDependent":false,"Game":"Ultimate","Related":{"Smash4":{"Character":"http://api.kuroganehammer.com/api/characters/name/MetaKnight?game=smash4"},"Ultimate":{"Character":"http://api.kuroganehammer.com/api/characters/name/MetaKnight?game=ultimate","Self":"http://api.kuroganehammer.com/api/moves/7a6c53bcfab644cbbf675b67c78aad45?game=ultimate"}},"Links":[{"Rel":"self","Href":"http://api.kuroganehammer.com/api/moves/7a6c53bcfab644cbbf675b67c78aad45?game=ultimate"},{"Rel":"character","Href":"http://api.kuroganehammer.com/api/characters/name/MetaKnight?game=ultimate"}]},{"InstanceId":"0f7c1e845a224973bd7b217752c5be05","Name":"Fair (Hits 1-2)","OwnerId":30,"Owner":"MetaKnight","HitboxActive":"9, 12","FirstActionableFrame":"46","BaseDamage":"1.5","Angle":"367/367/60/60","BaseKnockBackSetKnockback":"F: 40/40/B: 60/60","LandingLag":"10","AutoCancel":"44>","KnockbackGrowth":"100","MoveType":"aerial","IsWeightDependent":false,"Game":"Ultimate","Related":{"Smash4":{"Character":"http://api.kuroganehammer.com/api/characters/name/MetaKnight?game=smash4"},"Ultimate":{"Character":"http://api.kuroganehammer.com/api/characters/name/MetaKnight?game=ultimate","Self":"http://api.kuroganehammer.com/api/moves/0f7c1e845a224973bd7b217752c5be05?game=ultimate"}},"Links":[{"Rel":"self","Href":"http://api.kuroganehammer.com/api/moves/0f7c1e845a224973bd7b217752c5be05?game=ultimate"},{"Rel":"character","Href":"http://api.kuroganehammer.com/api/characters/name/MetaKnight?game=ultimate"}]},{"InstanceId":"3ce5338fbbb94809a2cb916918e6f2e1","Name":"Fair (Hit 3)","OwnerId":30,"Owner":"MetaKnight","HitboxActive":"15","FirstActionableFrame":"-","BaseDamage":"3","Angle":"48","BaseKnockBackSetKnockback":"60","LandingLag":"-","AutoCancel":"-","KnockbackGrowth":"140","MoveType":"aerial","IsWeightDependent":false,"Game":"Ultimate","Related":{"Smash4":{"Character":"http://api.kuroganehammer.com/api/characters/name/MetaKnight?game=smash4"},"Ultimate":{"Character":"http://api.kuroganehammer.com/api/characters/name/MetaKnight?game=ultimate","Self":"http://api.kuroganehammer.com/api/moves/3ce5338fbbb94809a2cb916918e6f2e1?game=ultimate"}},"Links":[{"Rel":"self","Href":"http://api.kuroganehammer.com/api/moves/3ce5338fbbb94809a2cb916918e6f2e1?game=ultimate"},{"Rel":"character","Href":"http://api.kuroganehammer.com/api/characters/name/MetaKnight?game=ultimate"}]},{"InstanceId":"5617b311422e4fa8be6fcfa36e996044","Name":"Bair (Hits 1-2)","OwnerId":30,"Owner":"MetaKnight","HitboxActive":"7-8, 13-14","FirstActionableFrame":"52","BaseDamage":"1.5","Angle":"367/367/55/55","BaseKnockBackSetKnockback":"F: 90/90/B: 50/50","LandingLag":"11","AutoCancel":"1-6, 40>","KnockbackGrowth":"100/100/90/90","MoveType":"aerial","IsWeightDependent":false,"Game":"Ultimate","Related":{"Smash4":{"Character":"http://api.kuroganehammer.com/api/characters/name/MetaKnight?game=smash4"},"Ultimate":{"Character":"http://api.kuroganehammer.com/api/characters/name/MetaKnight?game=ultimate","Self":"http://api.kuroganehammer.com/api/moves/5617b311422e4fa8be6fcfa36e996044?game=ultimate"}},"Links":[{"Rel":"self","Href":"http://api.kuroganehammer.com/api/moves/5617b311422e4fa8be6fcfa36e996044?game=ultimate"},{"Rel":"character","Href":"http://api.kuroganehammer.com/api/characters/name/MetaKnight?game=ultimate"}]},{"InstanceId":"ebd2c046fb344728adb5e6e6acb1f533","Name":"Bair (Hit 3)","OwnerId":30,"Owner":"MetaKnight","HitboxActive":"20-21","FirstActionableFrame":"-","BaseDamage":"4","Angle":"361","BaseKnockBackSetKnockback":"30","LandingLag":"-","AutoCancel":"-","KnockbackGrowth":"198","MoveType":"aerial","IsWeightDependent":false,"Game":"Ultimate","Related":{"Smash4":{"Character":"http://api.kuroganehammer.com/api/characters/name/MetaKnight?game=smash4"},"Ultimate":{"Character":"http://api.kuroganehammer.com/api/characters/name/MetaKnight?game=ultimate","Self":"http://api.kuroganehammer.com/api/moves/ebd2c046fb344728adb5e6e6acb1f533?game=ultimate"}},"Links":[{"Rel":"self","Href":"http://api.kuroganehammer.com/api/moves/ebd2c046fb344728adb5e6e6acb1f533?game=ultimate"},{"Rel":"character","Href":"http://api.kuroganehammer.com/api/characters/name/MetaKnight?game=ultimate"}]},{"InstanceId":"cdce3d149f774538bfc4b19b104fda5e","Name":"Uair","OwnerId":30,"Owner":"MetaKnight","HitboxActive":"6","FirstActionableFrame":"27","BaseDamage":"4","Angle":"67/67/50","BaseKnockBackSetKnockback":"30","LandingLag":"9","AutoCancel":"1-5, 24>","KnockbackGrowth":"128","MoveType":"aerial","IsWeightDependent":false,"Game":"Ultimate","Related":{"Smash4":{"Character":"http://api.kuroganehammer.com/api/characters/name/MetaKnight?game=smash4"},"Ultimate":{"Character":"http://api.kuroganehammer.com/api/characters/name/MetaKnight?game=ultimate","Self":"http://api.kuroganehammer.com/api/moves/cdce3d149f774538bfc4b19b104fda5e?game=ultimate"}},"Links":[{"Rel":"self","Href":"http://api.kuroganehammer.com/api/moves/cdce3d149f774538bfc4b19b104fda5e?game=ultimate"},{"Rel":"character","Href":"http://api.kuroganehammer.com/api/characters/name/MetaKnight?game=ultimate"}]},{"InstanceId":"c86bb4b650fc436ea69fe5b3ccd12849","Name":"Dair","OwnerId":30,"Owner":"MetaKnight","HitboxActive":"4","FirstActionableFrame":"28","BaseDamage":"6","Angle":"35/50/50","BaseKnockBackSetKnockback":"30","LandingLag":"9","AutoCancel":"1-3, 26>","KnockbackGrowth":"108","MoveType":"aerial","IsWeightDependent":false,"Game":"Ultimate","Related":{"Smash4":{"Character":"http://api.kuroganehammer.com/api/characters/name/MetaKnight?game=smash4"},"Ultimate":{"Character":"http://api.kuroganehammer.com/api/characters/name/MetaKnight?game=ultimate","Self":"http://api.kuroganehammer.com/api/moves/c86bb4b650fc436ea69fe5b3ccd12849?game=ultimate"}},"Links":[{"Rel":"self","Href":"http://api.kuroganehammer.com/api/moves/c86bb4b650fc436ea69fe5b3ccd12849?game=ultimate"},{"Rel":"character","Href":"http://api.kuroganehammer.com/api/characters/name/MetaKnight?game=ultimate"}]},{"InstanceId":"0cacd4a389d849b4a9b072a6e9dcbe37","Name":"Mach Tornado (Windboxes)","OwnerId":30,"Owner":"MetaKnight","HitboxActive":"12-46","FirstActionableFrame":"","BaseDamage":"0","Angle":"180","BaseKnockBackSetKnockback":"30","LandingLag":null,"AutoCancel":null,"KnockbackGrowth":"100","MoveType":"special","IsWeightDependent":false,"Game":"Ultimate","Related":{"Smash4":{"Character":"http://api.kuroganehammer.com/api/characters/name/MetaKnight?game=smash4"},"Ultimate":{"Character":"http://api.kuroganehammer.com/api/characters/name/MetaKnight?game=ultimate","Self":"http://api.kuroganehammer.com/api/moves/0cacd4a389d849b4a9b072a6e9dcbe37?game=ultimate"}},"Links":[{"Rel":"self","Href":"http://api.kuroganehammer.com/api/moves/0cacd4a389d849b4a9b072a6e9dcbe37?game=ultimate"},{"Rel":"character","Href":"http://api.kuroganehammer.com/api/characters/name/MetaKnight?game=ultimate"}]},{"InstanceId":"6821a12385474519be53c7f40451fada","Name":"Mach Tornado","OwnerId":30,"Owner":"MetaKnight","HitboxActive":"12-21","FirstActionableFrame":"-","BaseDamage":"12","Angle":"361","BaseKnockBackSetKnockback":"90","LandingLag":null,"AutoCancel":null,"KnockbackGrowth":"42","MoveType":"special","IsWeightDependent":false,"Game":"Ultimate","Related":{"Smash4":{"Character":"http://api.kuroganehammer.com/api/characters/name/MetaKnight?game=smash4"},"Ultimate":{"Character":"http://api.kuroganehammer.com/api/characters/name/MetaKnight?game=ultimate","Self":"http://api.kuroganehammer.com/api/moves/6821a12385474519be53c7f40451fada?game=ultimate"}},"Links":[{"Rel":"self","Href":"http://api.kuroganehammer.com/api/moves/6821a12385474519be53c7f40451fada?game=ultimate"},{"Rel":"character","Href":"http://api.kuroganehammer.com/api/characters/name/MetaKnight?game=ultimate"}]},{"InstanceId":"13d078bee568414aa34ff7f5367eb37f","Name":"Mach Tornado (Late)","OwnerId":30,"Owner":"MetaKnight","HitboxActive":"22-46","FirstActionableFrame":"-","BaseDamage":"8","Angle":"361","BaseKnockBackSetKnockback":"70","LandingLag":null,"AutoCancel":null,"KnockbackGrowth":"60","MoveType":"special","IsWeightDependent":false,"Game":"Ultimate","Related":{"Smash4":{"Character":"http://api.kuroganehammer.com/api/characters/name/MetaKnight?game=smash4"},"Ultimate":{"Character":"http://api.kuroganehammer.com/api/characters/name/MetaKnight?game=ultimate","Self":"http://api.kuroganehammer.com/api/moves/13d078bee568414aa34ff7f5367eb37f?game=ultimate"}},"Links":[{"Rel":"self","Href":"http://api.kuroganehammer.com/api/moves/13d078bee568414aa34ff7f5367eb37f?game=ultimate"},{"Rel":"character","Href":"http://api.kuroganehammer.com/api/characters/name/MetaKnight?game=ultimate"}]},{"InstanceId":"327739bb2a01439f9da6e964895f3c86","Name":"Drill Rush","OwnerId":30,"Owner":"MetaKnight","HitboxActive":"26-69","FirstActionableFrame":"-","BaseDamage":"1.1","Angle":"363/367/30/30/367/365","BaseKnockBackSetKnockback":"F: 45/30/45/45/0/0 B: 50/80/50/80/25/25","LandingLag":null,"AutoCancel":null,"KnockbackGrowth":"50","MoveType":"special","IsWeightDependent":false,"Game":"Ultimate","Related":{"Smash4":{"Character":"http://api.kuroganehammer.com/api/characters/name/MetaKnight?game=smash4"},"Ultimate":{"Character":"http://api.kuroganehammer.com/api/characters/name/MetaKnight?game=ultimate","Self":"http://api.kuroganehammer.com/api/moves/327739bb2a01439f9da6e964895f3c86?game=ultimate"}},"Links":[{"Rel":"self","Href":"http://api.kuroganehammer.com/api/moves/327739bb2a01439f9da6e964895f3c86?game=ultimate"},{"Rel":"character","Href":"http://api.kuroganehammer.com/api/characters/name/MetaKnight?game=ultimate"}]},{"InstanceId":"c1a2c0c57772445984a30c10dbd9f123","Name":"Drill Rush (Final Hit)","OwnerId":30,"Owner":"MetaKnight","HitboxActive":"70","FirstActionableFrame":"-","BaseDamage":"3","Angle":"40","BaseKnockBackSetKnockback":"40","LandingLag":null,"AutoCancel":null,"KnockbackGrowth":"185","MoveType":"special","IsWeightDependent":false,"Game":"Ultimate","Related":{"Smash4":{"Character":"http://api.kuroganehammer.com/api/characters/name/MetaKnight?game=smash4"},"Ultimate":{"Character":"http://api.kuroganehammer.com/api/characters/name/MetaKnight?game=ultimate","Self":"http://api.kuroganehammer.com/api/moves/c1a2c0c57772445984a30c10dbd9f123?game=ultimate"}},"Links":[{"Rel":"self","Href":"http://api.kuroganehammer.com/api/moves/c1a2c0c57772445984a30c10dbd9f123?game=ultimate"},{"Rel":"character","Href":"http://api.kuroganehammer.com/api/characters/name/MetaKnight?game=ultimate"}]},{"InstanceId":"2718504ae22444a0a9543d6e06c5662d","Name":"Shuttle Loop (Grounded, Hit 1, Early)","OwnerId":30,"Owner":"MetaKnight","HitboxActive":"8","FirstActionableFrame":"-","BaseDamage":"9","Angle":"86/88/86/88","BaseKnockBackSetKnockback":"F: 125/125/120/120","LandingLag":null,"AutoCancel":null,"KnockbackGrowth":"120","MoveType":"special","IsWeightDependent":false,"Game":"Ultimate","Related":{"Smash4":{"Character":"http://api.kuroganehammer.com/api/characters/name/MetaKnight?game=smash4"},"Ultimate":{"Character":"http://api.kuroganehammer.com/api/characters/name/MetaKnight?game=ultimate","Self":"http://api.kuroganehammer.com/api/moves/2718504ae22444a0a9543d6e06c5662d?game=ultimate"}},"Links":[{"Rel":"self","Href":"http://api.kuroganehammer.com/api/moves/2718504ae22444a0a9543d6e06c5662d?game=ultimate"},{"Rel":"character","Href":"http://api.kuroganehammer.com/api/characters/name/MetaKnight?game=ultimate"}]},{"InstanceId":"cc52059ef18f4ef9961428e7f4515363","Name":"Shuttle Loop (Grounded, Hit 1)","OwnerId":30,"Owner":"MetaKnight","HitboxActive":"9-10","FirstActionableFrame":"-","BaseDamage":"6","Angle":"86","BaseKnockBackSetKnockback":"F: 100","LandingLag":null,"AutoCancel":null,"KnockbackGrowth":"120","MoveType":"special","IsWeightDependent":false,"Game":"Ultimate","Related":{"Smash4":{"Character":"http://api.kuroganehammer.com/api/characters/name/MetaKnight?game=smash4"},"Ultimate":{"Character":"http://api.kuroganehammer.com/api/characters/name/MetaKnight?game=ultimate","Self":"http://api.kuroganehammer.com/api/moves/cc52059ef18f4ef9961428e7f4515363?game=ultimate"}},"Links":[{"Rel":"self","Href":"http://api.kuroganehammer.com/api/moves/cc52059ef18f4ef9961428e7f4515363?game=ultimate"},{"Rel":"character","Href":"http://api.kuroganehammer.com/api/characters/name/MetaKnight?game=ultimate"}]},{"InstanceId":"eb8ba4b935134f51840f3b6931ecc9e8","Name":"Shuttle Loop (Grounded, Hit 1, Late)","OwnerId":30,"Owner":"MetaKnight","HitboxActive":"11-12","FirstActionableFrame":"-","BaseDamage":"6","Angle":"86","BaseKnockBackSetKnockback":"F: 80","LandingLag":null,"AutoCancel":null,"KnockbackGrowth":"100","MoveType":"special","IsWeightDependent":false,"Game":"Ultimate","Related":{"Smash4":{"Character":"http://api.kuroganehammer.com/api/characters/name/MetaKnight?game=smash4"},"Ultimate":{"Character":"http://api.kuroganehammer.com/api/characters/name/MetaKnight?game=ultimate","Self":"http://api.kuroganehammer.com/api/moves/eb8ba4b935134f51840f3b6931ecc9e8?game=ultimate"}},"Links":[{"Rel":"self","Href":"http://api.kuroganehammer.com/api/moves/eb8ba4b935134f51840f3b6931ecc9e8?game=ultimate"},{"Rel":"character","Href":"http://api.kuroganehammer.com/api/characters/name/MetaKnight?game=ultimate"}]},{"InstanceId":"713e8963720e49ca9e18d7fef5cf9c60","Name":"Shuttle Loop  (Grounded, Hit 2)","OwnerId":30,"Owner":"MetaKnight","HitboxActive":"22-27","FirstActionableFrame":"-","BaseDamage":"6","Angle":"80","BaseKnockBackSetKnockback":"55","LandingLag":null,"AutoCancel":null,"KnockbackGrowth":"130","MoveType":"special","IsWeightDependent":false,"Game":"Ultimate","Related":{"Smash4":{"Character":"http://api.kuroganehammer.com/api/characters/name/MetaKnight?game=smash4"},"Ultimate":{"Character":"http://api.kuroganehammer.com/api/characters/name/MetaKnight?game=ultimate","Self":"http://api.kuroganehammer.com/api/moves/713e8963720e49ca9e18d7fef5cf9c60?game=ultimate"}},"Links":[{"Rel":"self","Href":"http://api.kuroganehammer.com/api/moves/713e8963720e49ca9e18d7fef5cf9c60?game=ultimate"},{"Rel":"character","Href":"http://api.kuroganehammer.com/api/characters/name/MetaKnight?game=ultimate"}]},{"InstanceId":"eb6082eb1ec0415fb7576dd35f943338","Name":"Shuttle Loop (Aerial, Hit 1)","OwnerId":30,"Owner":"MetaKnight","HitboxActive":"7","FirstActionableFrame":"-","BaseDamage":"6","Angle":"88/86","BaseKnockBackSetKnockback":"F: 116/110","LandingLag":null,"AutoCancel":null,"KnockbackGrowth":"120","MoveType":"special","IsWeightDependent":false,"Game":"Ultimate","Related":{"Smash4":{"Character":"http://api.kuroganehammer.com/api/characters/name/MetaKnight?game=smash4"},"Ultimate":{"Character":"http://api.kuroganehammer.com/api/characters/name/MetaKnight?game=ultimate","Self":"http://api.kuroganehammer.com/api/moves/eb6082eb1ec0415fb7576dd35f943338?game=ultimate"}},"Links":[{"Rel":"self","Href":"http://api.kuroganehammer.com/api/moves/eb6082eb1ec0415fb7576dd35f943338?game=ultimate"},{"Rel":"character","Href":"http://api.kuroganehammer.com/api/characters/name/MetaKnight?game=ultimate"}]},{"InstanceId":"f11a36bf419a41f785f8342b47f21ac2","Name":"Shuttle Loop (Aerial, Hit 1, Late)","OwnerId":30,"Owner":"MetaKnight","HitboxActive":"8-10","FirstActionableFrame":"-","BaseDamage":"6","Angle":"86","BaseKnockBackSetKnockback":"F: 80","LandingLag":null,"AutoCancel":null,"KnockbackGrowth":"100","MoveType":"special","IsWeightDependent":false,"Game":"Ultimate","Related":{"Smash4":{"Character":"http://api.kuroganehammer.com/api/characters/name/MetaKnight?game=smash4"},"Ultimate":{"Character":"http://api.kuroganehammer.com/api/characters/name/MetaKnight?game=ultimate","Self":"http://api.kuroganehammer.com/api/moves/f11a36bf419a41f785f8342b47f21ac2?game=ultimate"}},"Links":[{"Rel":"self","Href":"http://api.kuroganehammer.com/api/moves/f11a36bf419a41f785f8342b47f21ac2?game=ultimate"},{"Rel":"character","Href":"http://api.kuroganehammer.com/api/characters/name/MetaKnight?game=ultimate"}]},{"InstanceId":"bbcf72fbf036449dbf5dd8aa3f775a6b","Name":"Shuttle Loop (Aerial, Hit 2)","OwnerId":30,"Owner":"MetaKnight","HitboxActive":"20-26","FirstActionableFrame":"-","BaseDamage":"6","Angle":"80","BaseKnockBackSetKnockback":"55","LandingLag":null,"AutoCancel":null,"KnockbackGrowth":"118","MoveType":"special","IsWeightDependent":false,"Game":"Ultimate","Related":{"Smash4":{"Character":"http://api.kuroganehammer.com/api/characters/name/MetaKnight?game=smash4"},"Ultimate":{"Character":"http://api.kuroganehammer.com/api/characters/name/MetaKnight?game=ultimate","Self":"http://api.kuroganehammer.com/api/moves/bbcf72fbf036449dbf5dd8aa3f775a6b?game=ultimate"}},"Links":[{"Rel":"self","Href":"http://api.kuroganehammer.com/api/moves/bbcf72fbf036449dbf5dd8aa3f775a6b?game=ultimate"},{"Rel":"character","Href":"http://api.kuroganehammer.com/api/characters/name/MetaKnight?game=ultimate"}]},{"InstanceId":"e184affb4dfa4c2cae49e8250a809426","Name":"Dimensional Cape","OwnerId":30,"Owner":"MetaKnight","HitboxActive":"Intangible: 12-39","FirstActionableFrame":"58","BaseDamage":"-","Angle":"-","BaseKnockBackSetKnockback":"-","LandingLag":null,"AutoCancel":null,"KnockbackGrowth":"-","MoveType":"special","IsWeightDependent":false,"Game":"Ultimate","Related":{"Smash4":{"Character":"http://api.kuroganehammer.com/api/characters/name/MetaKnight?game=smash4"},"Ultimate":{"Character":"http://api.kuroganehammer.com/api/characters/name/MetaKnight?game=ultimate","Self":"http://api.kuroganehammer.com/api/moves/e184affb4dfa4c2cae49e8250a809426?game=ultimate"}},"Links":[{"Rel":"self","Href":"http://api.kuroganehammer.com/api/moves/e184affb4dfa4c2cae49e8250a809426?game=ultimate"},{"Rel":"character","Href":"http://api.kuroganehammer.com/api/characters/name/MetaKnight?game=ultimate"}]},{"InstanceId":"d69e97b3889a441f98ee9b17f5d4162a","Name":"Dimensional Cape (Grounded, Forward)","OwnerId":30,"Owner":"MetaKnight","HitboxActive":"34","FirstActionableFrame":"93","BaseDamage":"16","Angle":"53","BaseKnockBackSetKnockback":"40","LandingLag":null,"AutoCancel":null,"KnockbackGrowth":"98","MoveType":"special","IsWeightDependent":false,"Game":"Ultimate","Related":{"Smash4":{"Character":"http://api.kuroganehammer.com/api/characters/name/MetaKnight?game=smash4"},"Ultimate":{"Character":"http://api.kuroganehammer.com/api/characters/name/MetaKnight?game=ultimate","Self":"http://api.kuroganehammer.com/api/moves/d69e97b3889a441f98ee9b17f5d4162a?game=ultimate"}},"Links":[{"Rel":"self","Href":"http://api.kuroganehammer.com/api/moves/d69e97b3889a441f98ee9b17f5d4162a?game=ultimate"},{"Rel":"character","Href":"http://api.kuroganehammer.com/api/characters/name/MetaKnight?game=ultimate"}]},{"InstanceId":"e2ea0763cf91470587019bd7e3213c3c","Name":"Dimensional Cape (Grounded)","OwnerId":30,"Owner":"MetaKnight","HitboxActive":"34","FirstActionableFrame":"93","BaseDamage":"16","Angle":"53","BaseKnockBackSetKnockback":"40","LandingLag":null,"AutoCancel":null,"KnockbackGrowth":"98","MoveType":"special","IsWeightDependent":false,"Game":"Ultimate","Related":{"Smash4":{"Character":"http://api.kuroganehammer.com/api/characters/name/MetaKnight?game=smash4"},"Ultimate":{"Character":"http://api.kuroganehammer.com/api/characters/name/MetaKnight?game=ultimate","Self":"http://api.kuroganehammer.com/api/moves/e2ea0763cf91470587019bd7e3213c3c?game=ultimate"}},"Links":[{"Rel":"self","Href":"http://api.kuroganehammer.com/api/moves/e2ea0763cf91470587019bd7e3213c3c?game=ultimate"},{"Rel":"character","Href":"http://api.kuroganehammer.com/api/characters/name/MetaKnight?game=ultimate"}]},{"InstanceId":"58a8fbcbd0be454e95cada703dc0d898","Name":"Dimensional Cape (Grounded, Back)","OwnerId":30,"Owner":"MetaKnight","HitboxActive":"34","FirstActionableFrame":"93","BaseDamage":"13","Angle":"53","BaseKnockBackSetKnockback":"40","LandingLag":null,"AutoCancel":null,"KnockbackGrowth":"98","MoveType":"special","IsWeightDependent":false,"Game":"Ultimate","Related":{"Smash4":{"Character":"http://api.kuroganehammer.com/api/characters/name/MetaKnight?game=smash4"},"Ultimate":{"Character":"http://api.kuroganehammer.com/api/characters/name/MetaKnight?game=ultimate","Self":"http://api.kuroganehammer.com/api/moves/58a8fbcbd0be454e95cada703dc0d898?game=ultimate"}},"Links":[{"Rel":"self","Href":"http://api.kuroganehammer.com/api/moves/58a8fbcbd0be454e95cada703dc0d898?game=ultimate"},{"Rel":"character","Href":"http://api.kuroganehammer.com/api/characters/name/MetaKnight?game=ultimate"}]},{"InstanceId":"e563a580e8694299b8d9543149f13d15","Name":"Dimensional Cape (Aerial, Forward)","OwnerId":30,"Owner":"MetaKnight","HitboxActive":"34","FirstActionableFrame":"93","BaseDamage":"16","Angle":"53","BaseKnockBackSetKnockback":"40","LandingLag":null,"AutoCancel":null,"KnockbackGrowth":"98","MoveType":"special","IsWeightDependent":false,"Game":"Ultimate","Related":{"Smash4":{"Character":"http://api.kuroganehammer.com/api/characters/name/MetaKnight?game=smash4"},"Ultimate":{"Character":"http://api.kuroganehammer.com/api/characters/name/MetaKnight?game=ultimate","Self":"http://api.kuroganehammer.com/api/moves/e563a580e8694299b8d9543149f13d15?game=ultimate"}},"Links":[{"Rel":"self","Href":"http://api.kuroganehammer.com/api/moves/e563a580e8694299b8d9543149f13d15?game=ultimate"},{"Rel":"character","Href":"http://api.kuroganehammer.com/api/characters/name/MetaKnight?game=ultimate"}]},{"InstanceId":"84179d9d875344f88b6415747a110ccb","Name":"Dimensional Cape (Aerial)","OwnerId":30,"Owner":"MetaKnight","HitboxActive":"34","FirstActionableFrame":"93","BaseDamage":"16","Angle":"53","BaseKnockBackSetKnockback":"40","LandingLag":null,"AutoCancel":null,"KnockbackGrowth":"98","MoveType":"special","IsWeightDependent":false,"Game":"Ultimate","Related":{"Smash4":{"Character":"http://api.kuroganehammer.com/api/characters/name/MetaKnight?game=smash4"},"Ultimate":{"Character":"http://api.kuroganehammer.com/api/characters/name/MetaKnight?game=ultimate","Self":"http://api.kuroganehammer.com/api/moves/84179d9d875344f88b6415747a110ccb?game=ultimate"}},"Links":[{"Rel":"self","Href":"http://api.kuroganehammer.com/api/moves/84179d9d875344f88b6415747a110ccb?game=ultimate"},{"Rel":"character","Href":"http://api.kuroganehammer.com/api/characters/name/MetaKnight?game=ultimate"}]},{"InstanceId":"04b9555817ac4c6abe0b576b295a9cb6","Name":"Dimensional Cape (Aerial, Back)","OwnerId":30,"Owner":"MetaKnight","HitboxActive":"34","FirstActionableFrame":"93","BaseDamage":"14","Angle":"53","BaseKnockBackSetKnockback":"40","LandingLag":null,"AutoCancel":null,"KnockbackGrowth":"98","MoveType":"special","IsWeightDependent":false,"Game":"Ultimate","Related":{"Smash4":{"Character":"http://api.kuroganehammer.com/api/characters/name/MetaKnight?game=smash4"},"Ultimate":{"Character":"http://api.kuroganehammer.com/api/characters/name/MetaKnight?game=ultimate","Self":"http://api.kuroganehammer.com/api/moves/04b9555817ac4c6abe0b576b295a9cb6?game=ultimate"}},"Links":[{"Rel":"self","Href":"http://api.kuroganehammer.com/api/moves/04b9555817ac4c6abe0b576b295a9cb6?game=ultimate"},{"Rel":"character","Href":"http://api.kuroganehammer.com/api/characters/name/MetaKnight?game=ultimate"}]},{"InstanceId":"545a1706aa23448b9f1120a565e23db5","Name":"Fthrow","OwnerId":30,"Owner":"MetaKnight","HitboxActive":null,"FirstActionableFrame":null,"BaseDamage":"6, 3","Angle":"65","BaseKnockBackSetKnockback":"50","LandingLag":null,"AutoCancel":null,"KnockbackGrowth":"140","MoveType":"throw","IsWeightDependent":false,"Game":"Ultimate","Related":{"Smash4":{"Character":"http://api.kuroganehammer.com/api/characters/name/MetaKnight?game=smash4"},"Ultimate":{"Character":"http://api.kuroganehammer.com/api/characters/name/MetaKnight?game=ultimate","Self":"http://api.kuroganehammer.com/api/moves/545a1706aa23448b9f1120a565e23db5?game=ultimate"}},"Links":[{"Rel":"self","Href":"http://api.kuroganehammer.com/api/moves/545a1706aa23448b9f1120a565e23db5?game=ultimate"},{"Rel":"character","Href":"http://api.kuroganehammer.com/api/characters/name/MetaKnight?game=ultimate"}]},{"InstanceId":"e9ff026a639c4d1e9ce0bc60cf94184b","Name":"Bthrow","OwnerId":30,"Owner":"MetaKnight","HitboxActive":null,"FirstActionableFrame":null,"BaseDamage":"7, 3","Angle":"45","BaseKnockBackSetKnockback":"60","LandingLag":null,"AutoCancel":null,"KnockbackGrowth":"140","MoveType":"throw","IsWeightDependent":false,"Game":"Ultimate","Related":{"Smash4":{"Character":"http://api.kuroganehammer.com/api/characters/name/MetaKnight?game=smash4"},"Ultimate":{"Character":"http://api.kuroganehammer.com/api/characters/name/MetaKnight?game=ultimate","Self":"http://api.kuroganehammer.com/api/moves/e9ff026a639c4d1e9ce0bc60cf94184b?game=ultimate"}},"Links":[{"Rel":"self","Href":"http://api.kuroganehammer.com/api/moves/e9ff026a639c4d1e9ce0bc60cf94184b?game=ultimate"},{"Rel":"character","Href":"http://api.kuroganehammer.com/api/characters/name/MetaKnight?game=ultimate"}]},{"InstanceId":"2f78e30ae3b14c968807cc31b069940b","Name":"Uthrow","OwnerId":30,"Owner":"MetaKnight","HitboxActive":null,"FirstActionableFrame":null,"BaseDamage":"10","Angle":"77","BaseKnockBackSetKnockback":"70","LandingLag":null,"AutoCancel":null,"KnockbackGrowth":"70","MoveType":"throw","IsWeightDependent":false,"Game":"Ultimate","Related":{"Smash4":{"Character":"http://api.kuroganehammer.com/api/characters/name/MetaKnight?game=smash4"},"Ultimate":{"Character":"http://api.kuroganehammer.com/api/characters/name/MetaKnight?game=ultimate","Self":"http://api.kuroganehammer.com/api/moves/2f78e30ae3b14c968807cc31b069940b?game=ultimate"}},"Links":[{"Rel":"self","Href":"http://api.kuroganehammer.com/api/moves/2f78e30ae3b14c968807cc31b069940b?game=ultimate"},{"Rel":"character","Href":"http://api.kuroganehammer.com/api/characters/name/MetaKnight?game=ultimate"}]},{"InstanceId":"882cb744ac794d6286fb589328eecd8e","Name":"Dthrow","OwnerId":30,"Owner":"MetaKnight","HitboxActive":null,"FirstActionableFrame":null,"BaseDamage":"0.5%×9, 1, 2","Angle":"60","BaseKnockBackSetKnockback":"50","LandingLag":null,"AutoCancel":null,"KnockbackGrowth":"170","MoveType":"throw","IsWeightDependent":false,"Game":"Ultimate","Related":{"Smash4":{"Character":"http://api.kuroganehammer.com/api/characters/name/MetaKnight?game=smash4"},"Ultimate":{"Character":"http://api.kuroganehammer.com/api/characters/name/MetaKnight?game=ultimate","Self":"http://api.kuroganehammer.com/api/moves/882cb744ac794d6286fb589328eecd8e?game=ultimate"}},"Links":[{"Rel":"self","Href":"http://api.kuroganehammer.com/api/moves/882cb744ac794d6286fb589328eecd8e?game=ultimate"},{"Rel":"character","Href":"http://api.kuroganehammer.com/api/characters/name/MetaKnight?game=ultimate"}]}]