[{"InstanceId":"cc9d980611ed4b538a337783272d23da","Name":"AerialJump","OwnerId":40,"Owner":"Peach","Values":[{"Value":"30.025824","Owner":"Peach","OwnerId":40,"Name":"HEIGHT"}],"Game":"Smash4","Related":{"Smash4":{"Character":"http://api.kuroganehammer.com/api/characters/name/Peach?game=smash4","Self":"http://api.kuroganehammer.com/api/characterattributes/cc9d980611ed4b538a337783272d23da?game=smash4"},"Ultimate":{"Character":"http://api.kuroganehammer.com/api/characters/name/Peach?game=ultimate"}},"Links":[{"Rel":"self","Href":"http://api.kuroganehammer.com/api/characterattributes/cc9d980611ed4b538a337783272d23da?game=smash4"},{"Rel":"character","Href":"http://api.kuroganehammer.com/api/characters/name/Peach?game=smash4"}]},{"InstanceId":"19ff0be2a3004665bef7be9de5af824d","Name":"AirAcceleration","OwnerId":40,"Owner":"Peach","Values":[{"Value":"0.1","Owner":"Peach","OwnerId":40,"Name":"MAX ADDITIONAL"},{"Value":"0.01","Owner":"Peach","OwnerId":40,"Name":"BASE VALUE"},{"Value":"0.11","Owner":"Peach","OwnerId":40,"Name":"TOTAL"}],"Game":"Smash4","Related":{"Smash4":{"Character":"http://api.kuroganehammer.com/api/characters/name/Peach?game=smash4","Self":"http://api.kuroganehammer.com/api/characterattributes/19ff0be2a3004665bef7be9de5af824d?game=smash4"},"Ultimate":{"Character":"http://api.kuroganehammer.com/api/characters/name/Peach?game=ultimate"}},"Links":[{"Rel":"self","Href":"http://api.kuroganehammer.com/api/characterattributes/19ff0be2a3004665bef7be9de5af824d?game=smash4"},{"Rel":"character","Href":"http://api.kuroganehammer.com/api/characters/name/Peach?game=smash4"}]},{"InstanceId":"a80fe09917ac42c599fe75479d8b8d31","Name":"AirDodge","OwnerId":40,"Owner":"Peach","Values":[{"Value":"3-28","Owner":"Peach","OwnerId":40,"Name":"INTANGIBLE"},{"Value":"34","Owner":"Peach","OwnerId":40,"Name":"FAF"}],"Game":"Smash4","Related":{"Smash4":{"Character":"http://api.kuroganehammer.com/api/characters/name/Peach?game=smash4","Self":"http://api.kuroganehammer.com/api/characterattributes/a80fe09917ac42c599fe75479d8b8d31?game=smash4"},"Ultimate":{"Character":"http://api.kuroganehammer.com/api/characters/name/Peach?game=ultimate"}},"Links":[{"Rel":"self","Href":"http://api.kuroganehammer.com/api/characterattributes/a80fe09917ac42c599fe75479d8b8d31?game=smash4"},{"Rel":"character","Href":"http://api.kuroganehammer.com/api/characters/name/Peach?game=smash4"}]},{"InstanceId":"36d2678ac05242748f957112cc28bf6c","Name":"AirFriction","OwnerId":40,"Owner":"Peach","Values":[{"Value":"0.01","Owner":"Peach","OwnerId":40,"Name":"VALUE"}],"Game":"Smash4","Related":{"Smash4":{"Character":"http://api.kuroganehammer.com/api/characters/name/Peach?game=smash4","Self":"http://api.kuroganehammer.com/api/characterattributes/36d2678ac05242748f957112cc28bf6c?game=smash4"},"Ultimate":{"Character":"http://api.kuroganehammer.com/api/characters/name/Peach?game=ultimate"}},"Links":[{"Rel":"self","Href":"http://api.kuroganehammer.com/api/characterattributes/36d2678ac05242748f957112cc28bf6c?game=smash4"},{"Rel":"character","Href":"http://api.kuroganehammer.com/api/characters/name/Peach?game=smash4"}]},{"InstanceId":"9271a48b594147e185b574222aa7f6d0","Name":"AirSpeed","OwnerId":40,"Owner":"Peach","Values":[{"Value":"0.95","Owner":"Peach","OwnerId":40,"Name":"MAX AIR SPEED VALUE"}],"Game":"Smash4","Related":{"Smash4":{"Character":"http://api.kuroganehammer.com/api/characters/name/Peach?game=smash4","Self":"http://api.kuroganehammer.com/api/characterattributes/9271a48b594147e185b574222aa7f6d0?game=smash4"},"Ultimate":{"Character":"http://api.kuroganehammer.com/api/characters/name/Peach?game=ultimate"}},"Links":[{"Rel":"self","Href":"http://api.kuroganehammer.com/api/characterattributes/9271a48b594147e185b574222aa7f6d0?game=smash4"},{"Rel":"character","Href":"http://api.kuroganehammer.com/api/characters/name/Peach?game=smash4"}]},{"InstanceId":"35955bb20d8643ffb3030ede3c59ea64","Name":"Counters","OwnerId":40,"Owner":"Peach","Values":[{"Value":"10-34","Owner":"Peach","OwnerId":40,"Name":"COUNTER FRAMES"},{"Value":"11-14","Owner":"Peach","OwnerId":40,"Name":"INTANGIBLE ON"},{"Value":"63","Owner":"Peach","OwnerId":40,"Name":"FAF"},{"Value":"2","Owner":"Peach","OwnerId":40,"Name":"DAMAGE (MULTIPLIER)"},{"Value":"15 | 300","Owner":"Peach","OwnerId":40,"Name":"BKB | KBG"}],"Game":"Smash4","Related":{"Smash4":{"Character":"http://api.kuroganehammer.com/api/characters/name/Peach?game=smash4","Self":"http://api.kuroganehammer.com/api/characterattributes/35955bb20d8643ffb3030ede3c59ea64?game=smash4"},"Ultimate":{"Character":"http://api.kuroganehammer.com/api/characters/name/Peach?game=ultimate"}},"Links":[{"Rel":"self","Href":"http://api.kuroganehammer.com/api/characterattributes/35955bb20d8643ffb3030ede3c59ea64?game=smash4"},{"Rel":"character","Href":"http://api.kuroganehammer.com/api/characters/name/Peach?game=smash4"}]},{"InstanceId":"8cc8e94aa4724ae4b844e7065d3f1dde","Name":"FallSpeed","OwnerId":40,"Owner":"Peach","Values":[{"Value":"1.15","Owner":"Peach","OwnerId":40,"Name":"MAX FALL SPEED"},{"Value":"1.84","Owner":"Peach","OwnerId":40,"Name":"FAST FALL SPEED"},{"Value":"60%","Owner":"Peach","OwnerId":40,"Name":"SPEED INCREASE"}],"Game":"Smash4","Related":{"Smash4":{"Character":"http://api.kuroganehammer.com/api/characters/name/Peach?game=smash4","Self":"http://api.kuroganehammer.com/api/characterattributes/8cc8e94aa4724ae4b844e7065d3f1dde?game=smash4"},"Ultimate":{"Character":"http://api.kuroganehammer.com/api/characters/name/Peach?game=ultimate"}},"Links":[{"Rel":"self","Href":"http://api.kuroganehammer.com/api/characterattributes/8cc8e94aa4724ae4b844e7065d3f1dde?game=smash4"},{"Rel":"character","Href":"http://api.kuroganehammer.com/api/characters/name/Peach?game=smash4"}]},{"InstanceId":"3400386c2c484abc85caa061fb9c786b","Name":"FullHop","OwnerId":40,"Owner":"Peach","Values":[{"Value":"30.025824","Owner":"Peach","OwnerId":40,"Name":"HEIGHT"}],"Game":"Smash4","Related":{"Smash4":{"Character":"http://api.kuroganehammer.com/api/characters/name/Peach?game=smash4","Self":"http://api.kuroganehammer.com/api/characterattributes/3400386c2c484abc85caa061fb9c786b?game=smash4"},"Ultimate":{"Character":"http://api.kuroganehammer.com/api/characters/name/Peach?game=ultimate"}},"Links":[{"Rel":"self","Href":"http://api.kuroganehammer.com/api/characterattributes/3400386c2c484abc85caa061fb9c786b?game=smash4"},{"Rel":"character","Href":"http://api.kuroganehammer.com/api/characters/name/Peach?game=smash4"}]},{"InstanceId":"a57207eb3da046998ed7c9ca7a5c30b3","Name":"Gravity","OwnerId":40,"Owner":"Peach","Values":[{"Value":"0.068","Owner":"Peach","OwnerId":40,"Name":"VALUE"}],"Game":"Smash4","Related":{"Smash4":{"Character":"http://api.kuroganehammer.com/api/characters/name/Peach?game=smash4","Self":"http://api.kuroganehammer.com/api/characterattributes/a57207eb3da046998ed7c9ca7a5c30b3?game=smash4"},"Ultimate":{"Character":"http://api.kuroganehammer.com/api/characters/name/Peach?game=ultimate"}},"Links":[{"Rel":"self","Href":"http://api.kuroganehammer.com/api/characterattributes/a57207eb3da046998ed7c9ca7a5c30b3?game=smash4"},{"Rel":"character","Href":"http://api.kuroganehammer.com/api/characters/name/Peach?game=smash4"}]},{"InstanceId":"bc29762efb6a46b1b438b3b84d7c3f1e","Name":"JumpSquat","OwnerId":40,"Owner":"Peach","Values":[{"Value":"5","Owner":"Peach","OwnerId":40,"Name":"VALUE"}],"Game":"Smash4","Related":{"Smash4":{"Character":"http://api.kuroganehammer.com/api/characters/name/Peach?game=smash4","Self":"http://api.kuroganehammer.com/api/characterattributes/bc29762efb6a46b1b438b3b84d7c3f1e?game=smash4"},"Ultimate":{"Character":"http://api.kuroganehammer.com/api/characters/name/Peach?game=ultimate"}},"Links":[{"Rel":"self","Href":"http://api.kuroganehammer.com/api/characterattributes/bc29762efb6a46b1b438b3b84d7c3f1e?game=smash4"},{"Rel":"character","Href":"http://api.kuroganehammer.com/api/characters/name/Peach?game=smash4"}]},{"InstanceId":"92387e3268584c8c81f8feed0985b2dc","Name":"LedgeHop","OwnerId":40,"Owner":"Peach","Values":[{"Value":"35.012913","Owner":"Peach","OwnerId":40,"Name":"HEIGHT"}],"Game":"Smash4","Related":{"Smash4":{"Character":"http://api.kuroganehammer.com/api/characters/name/Peach?game=smash4","Self":"http://api.kuroganehammer.com/api/characterattributes/92387e3268584c8c81f8feed0985b2dc?game=smash4"},"Ultimate":{"Character":"http://api.kuroganehammer.com/api/characters/name/Peach?game=ultimate"}},"Links":[{"Rel":"self","Href":"http://api.kuroganehammer.com/api/characterattributes/92387e3268584c8c81f8feed0985b2dc?game=smash4"},{"Rel":"character","Href":"http://api.kuroganehammer.com/api/characters/name/Peach?game=smash4"}]},{"InstanceId":"ab68660905a04f4aa3c7a77573d5081b","Name":"Rolls","OwnerId":40,"Owner":"Peach","Values":[{"Value":"4-17","Owner":"Peach","OwnerId":40,"Name":"INTANGIBLE"},{"Value":"31","Owner":"Peach","OwnerId":40,"Name":"FAF"}],"Game":"Smash4","Related":{"Smash4":{"Character":"http://api.kuroganehammer.com/api/characters/name/Peach?game=smash4","Self":"http://api.kuroganehammer.com/api/characterattributes/ab68660905a04f4aa3c7a77573d5081b?game=smash4"},"Ultimate":{"Character":"http://api.kuroganehammer.com/api/characters/name/Peach?game=ultimate"}},"Links":[{"Rel":"self","Href":"http://api.kuroganehammer.com/api/characterattributes/ab68660905a04f4aa3c7a77573d5081b?game=smash4"},{"Rel":"character","Href":"http://api.kuroganehammer.com/api/characters/name/Peach?game=smash4"}]},{"InstanceId":"cdecda1a94f7426896092bbfddcbedd4","Name":"RunSpeed","OwnerId":40,"Owner":"Peach","Values":[{"Value":"1.4175","Owner":"Peach","OwnerId":40,"Name":"MAX RUN SPEED VALUE"}],"Game":"Smash4","Related":{"Smash4":{"Character":"http://api.kuroganehammer.com/api/characters/name/Peach?game=smash4","Self":"http://api.kuroganehammer.com/api/characterattributes/cdecda1a94f7426896092bbfddcbedd4?game=smash4"},"Ultimate":{"Character":"http://api.kuroganehammer.com/api/characters/name/Peach?game=ultimate"}},"Links":[{"Rel":"self","Href":"http://api.kuroganehammer.com/api/characterattributes/cdecda1a94f7426896092bbfddcbedd4?game=smash4"},{"Rel":"character","Href":"http://api.kuroganehammer.com/api/characters/name/Peach?game=smash4"}]},{"InstanceId":"039d9449123546f6bc4207be08079450","Name":"ShieldSize","OwnerId":40,"Owner":"Peach","Values":[{"Value":"10.5","Owner":"Peach","OwnerId":40,"Name":"SIZE"}],"Game":"Smash4","Related":{"Smash4":{"Character":"http://api.kuroganehammer.com/api/characters/name/Peach?game=smash4","Self":"http://api.kuroganehammer.com/api/characterattributes/039d9449123546f6bc4207be08079450?game=smash4"},"Ultimate":{"Character":"http://api.kuroganehammer.com/api/characters/name/Peach?game=ultimate"}},"Links":[{"Rel":"self","Href":"http://api.kuroganehammer.com/api/characterattributes/039d9449123546f6bc4207be08079450?game=smash4"},{"Rel":"character","Href":"http://api.kuroganehammer.com/api/characters/name/Peach?game=smash4"}]},{"InstanceId":"647055e7f3c44b7e911fdc49009e84cd","Name":"ShortHop","OwnerId":40,"Owner":"Peach","Values":[{"Value":"14.501237","Owner":"Peach","OwnerId":40,"Name":"HEIGHT"}],"Game":"Smash4","Related":{"Smash4":{"Character":"http://api.kuroganehammer.com/api/characters/name/Peach?game=smash4","Self":"http://api.kuroganehammer.com/api/characterattributes/647055e7f3c44b7e911fdc49009e84cd?game=smash4"},"Ultimate":{"Character":"http://api.kuroganehammer.com/api/characters/name/Peach?game=ultimate"}},"Links":[{"Rel":"self","Href":"http://api.kuroganehammer.com/api/characterattributes/647055e7f3c44b7e911fdc49009e84cd?game=smash4"},{"Rel":"character","Href":"http://api.kuroganehammer.com/api/characters/name/Peach?game=smash4"}]},{"InstanceId":"ba5fdafdd0ff4929bb959c096280f9d9","Name":"HardTrip","OwnerId":40,"Owner":"Peach","Values":[{"Value":"40","Owner":"Peach","OwnerId":40,"Name":"FAF"},{"Value":"1-5","Owner":"Peach","OwnerId":40,"Name":"INTANGIBLE"}],"Game":"Smash4","Related":{"Smash4":{"Character":"http://api.kuroganehammer.com/api/characters/name/Peach?game=smash4","Self":"http://api.kuroganehammer.com/api/characterattributes/ba5fdafdd0ff4929bb959c096280f9d9?game=smash4"},"Ultimate":{"Character":"http://api.kuroganehammer.com/api/characters/name/Peach?game=ultimate"}},"Links":[{"Rel":"self","Href":"http://api.kuroganehammer.com/api/characterattributes/ba5fdafdd0ff4929bb959c096280f9d9?game=smash4"},{"Rel":"character","Href":"http://api.kuroganehammer.com/api/characters/name/Peach?game=smash4"}]},{"InstanceId":"cadfaa9380ee4441b573b1ef01f0a670","Name":"SoftTrip","OwnerId":40,"Owner":"Peach","Values":[{"Value":"30","Owner":"Peach","OwnerId":40,"Name":"FAF"},{"Value":"1-5","Owner":"Peach","OwnerId":40,"Name":"INTANGIBLE"}],"Game":"Smash4","Related":{"Smash4":{"Character":"http://api.kuroganehammer.com/api/characters/name/Peach?game=smash4","Self":"http://api.kuroganehammer.com/api/characterattributes/cadfaa9380ee4441b573b1ef01f0a670?game=smash4"},"Ultimate":{"Character":"http://api.kuroganehammer.com/api/characters/name/Peach?game=ultimate"}},"Links":[{"Rel":"self","Href":"http://api.kuroganehammer.com/api/characterattributes/cadfaa9380ee4441b573b1ef01f0a670?game=smash4"},{"Rel":"character","Href":"http://api.kuroganehammer.com/api/characters/name/Peach?game=smash4"}]},{"InstanceId":"df6e52c1e2744f49a0e2228b80bc3d9d","Name":"Spotdodge","OwnerId":40,"Owner":"Peach","Values":[{"Value":"3-18","Owner":"Peach","OwnerId":40,"Name":"INTANGIBLE"},{"Value":"28","Owner":"Peach","OwnerId":40,"Name":"FAF"}],"Game":"Smash4","Related":{"Smash4":{"Character":"http://api.kuroganehammer.com/api/characters/name/Peach?game=smash4","Self":"http://api.kuroganehammer.com/api/characterattributes/df6e52c1e2744f49a0e2228b80bc3d9d?game=smash4"},"Ultimate":{"Character":"http://api.kuroganehammer.com/api/characters/name/Peach?game=ultimate"}},"Links":[{"Rel":"self","Href":"http://api.kuroganehammer.com/api/characterattributes/df6e52c1e2744f49a0e2228b80bc3d9d?game=smash4"},{"Rel":"character","Href":"http://api.kuroganehammer.com/api/characters/name/Peach?game=smash4"}]},{"InstanceId":"353cb921ea2644bea0d3f3a5d8f8781f","Name":"Traction","OwnerId":40,"Owner":"Peach","Values":[{"Value":"0.068","Owner":"Peach","OwnerId":40,"Name":"VALUE"}],"Game":"Smash4","Related":{"Smash4":{"Character":"http://api.kuroganehammer.com/api/characters/name/Peach?game=smash4","Self":"http://api.kuroganehammer.com/api/characterattributes/353cb921ea2644bea0d3f3a5d8f8781f?game=smash4"},"Ultimate":{"Character":"http://api.kuroganehammer.com/api/characters/name/Peach?game=ultimate"}},"Links":[{"Rel":"self","Href":"http://api.kuroganehammer.com/api/characterattributes/353cb921ea2644bea0d3f3a5d8f8781f?game=smash4"},{"Rel":"character","Href":"http://api.kuroganehammer.com/api/characters/name/Peach?game=smash4"}]},{"InstanceId":"bfd5159efdbb4c79a87b671dbda84bcf","Name":"GetUp On Back","OwnerId":40,"Owner":"Peach","Values":[{"Value":"30","Owner":"Peach","OwnerId":40,"Name":"FAF"},{"Value":"1-22","Owner":"Peach","OwnerId":40,"Name":"INTANGIBLE"}],"Game":"Smash4","Related":{"Smash4":{"Character":"http://api.kuroganehammer.com/api/characters/name/Peach?game=smash4","Self":"http://api.kuroganehammer.com/api/characterattributes/bfd5159efdbb4c79a87b671dbda84bcf?game=smash4"},"Ultimate":{"Character":"http://api.kuroganehammer.com/api/characters/name/Peach?game=ultimate"}},"Links":[{"Rel":"self","Href":"http://api.kuroganehammer.com/api/characterattributes/bfd5159efdbb4c79a87b671dbda84bcf?game=smash4"},{"Rel":"character","Href":"http://api.kuroganehammer.com/api/characters/name/Peach?game=smash4"}]},{"InstanceId":"b1a2e74fd0944cc2bc9a49c438bb9a7c","Name":"GetUp On Front","OwnerId":40,"Owner":"Peach","Values":[{"Value":"30","Owner":"Peach","OwnerId":40,"Name":"FAF"},{"Value":"1-22","Owner":"Peach","OwnerId":40,"Name":"INTANGIBLE"}],"Game":"Smash4","Related":{"Smash4":{"Character":"http://api.kuroganehammer.com/api/characters/name/Peach?game=smash4","Self":"http://api.kuroganehammer.com/api/characterattributes/b1a2e74fd0944cc2bc9a49c438bb9a7c?game=smash4"},"Ultimate":{"Character":"http://api.kuroganehammer.com/api/characters/name/Peach?game=ultimate"}},"Links":[{"Rel":"self","Href":"http://api.kuroganehammer.com/api/characterattributes/b1a2e74fd0944cc2bc9a49c438bb9a7c?game=smash4"},{"Rel":"character","Href":"http://api.kuroganehammer.com/api/characters/name/Peach?game=smash4"}]},{"InstanceId":"92c8c6c51b49428dab1b05850f76bd98","Name":"GetUp Back Roll Back","OwnerId":40,"Owner":"Peach","Values":[{"Value":"1-19","Owner":"Peach","OwnerId":40,"Name":"INTANGIBLE"},{"Value":"36","Owner":"Peach","OwnerId":40,"Name":"FAF"}],"Game":"Smash4","Related":{"Smash4":{"Character":"http://api.kuroganehammer.com/api/characters/name/Peach?game=smash4","Self":"http://api.kuroganehammer.com/api/characterattributes/92c8c6c51b49428dab1b05850f76bd98?game=smash4"},"Ultimate":{"Character":"http://api.kuroganehammer.com/api/characters/name/Peach?game=ultimate"}},"Links":[{"Rel":"self","Href":"http://api.kuroganehammer.com/api/characterattributes/92c8c6c51b49428dab1b05850f76bd98?game=smash4"},{"Rel":"character","Href":"http://api.kuroganehammer.com/api/characters/name/Peach?game=smash4"}]},{"InstanceId":"0fed6c984bdf4f6c8180bc2334e6f30f","Name":"GetUp Back Roll Front","OwnerId":40,"Owner":"Peach","Values":[{"Value":"1-19","Owner":"Peach","OwnerId":40,"Name":"INTANGIBLE"},{"Value":"36","Owner":"Peach","OwnerId":40,"Name":"FAF"}],"Game":"Smash4","Related":{"Smash4":{"Character":"http://api.kuroganehammer.com/api/characters/name/Peach?game=smash4","Self":"http://api.kuroganehammer.com/api/characterattributes/0fed6c984bdf4f6c8180bc2334e6f30f?game=smash4"},"Ultimate":{"Character":"http://api.kuroganehammer.com/api/characters/name/Peach?game=ultimate"}},"Links":[{"Rel":"self","Href":"http://api.kuroganehammer.com/api/characterattributes/0fed6c984bdf4f6c8180bc2334e6f30f?game=smash4"},{"Rel":"character","Href":"http://api.kuroganehammer.com/api/characters/name/Peach?game=smash4"}]},{"InstanceId":"ac91454787bd4eb092e1cdaa69e606f8","Name":"GetUp Forward Roll Back","OwnerId":40,"Owner":"Peach","Values":[{"Value":"1-19","Owner":"Peach","OwnerId":40,"Name":"INTANGIBLE"},{"Value":"36","Owner":"Peach","OwnerId":40,"Name":"FAF"}],"Game":"Smash4","Related":{"Smash4":{"Character":"http://api.kuroganehammer.com/api/characters/name/Peach?game=smash4","Self":"http://api.kuroganehammer.com/api/characterattributes/ac91454787bd4eb092e1cdaa69e606f8?game=smash4"},"Ultimate":{"Character":"http://api.kuroganehammer.com/api/characters/name/Peach?game=ultimate"}},"Links":[{"Rel":"self","Href":"http://api.kuroganehammer.com/api/characterattributes/ac91454787bd4eb092e1cdaa69e606f8?game=smash4"},{"Rel":"character","Href":"http://api.kuroganehammer.com/api/characters/name/Peach?game=smash4"}]},{"InstanceId":"e077333a5a19402ebd44f7fd5598c20e","Name":"GetUp Forward Roll Front","OwnerId":40,"Owner":"Peach","Values":[{"Value":"1-19","Owner":"Peach","OwnerId":40,"Name":"INTANGIBLE"},{"Value":"36","Owner":"Peach","OwnerId":40,"Name":"FAF"}],"Game":"Smash4","Related":{"Smash4":{"Character":"http://api.kuroganehammer.com/api/characters/name/Peach?game=smash4","Self":"http://api.kuroganehammer.com/api/characterattributes/e077333a5a19402ebd44f7fd5598c20e?game=smash4"},"Ultimate":{"Character":"http://api.kuroganehammer.com/api/characters/name/Peach?game=ultimate"}},"Links":[{"Rel":"self","Href":"http://api.kuroganehammer.com/api/characterattributes/e077333a5a19402ebd44f7fd5598c20e?game=smash4"},{"Rel":"character","Href":"http://api.kuroganehammer.com/api/characters/name/Peach?game=smash4"}]},{"InstanceId":"e7a0bd1346b74ae1ad025784a64aee82","Name":"Tech Frame Data","OwnerId":40,"Owner":"Peach","Values":[{"Value":"27","Owner":"Peach","OwnerId":40,"Name":"FAF"},{"Value":"1-20","Owner":"Peach","OwnerId":40,"Name":"INTANGIBLE"}],"Game":"Smash4","Related":{"Smash4":{"Character":"http://api.kuroganehammer.com/api/characters/name/Peach?game=smash4","Self":"http://api.kuroganehammer.com/api/characterattributes/e7a0bd1346b74ae1ad025784a64aee82?game=smash4"},"Ultimate":{"Character":"http://api.kuroganehammer.com/api/characters/name/Peach?game=ultimate"}},"Links":[{"Rel":"self","Href":"http://api.kuroganehammer.com/api/characterattributes/e7a0bd1346b74ae1ad025784a64aee82?game=smash4"},{"Rel":"character","Href":"http://api.kuroganehammer.com/api/characters/name/Peach?game=smash4"}]},{"InstanceId":"49ce73a38afc44aaadf5aa73439e4f60","Name":"Tech Roll Forward","OwnerId":40,"Owner":"Peach","Values":[{"Value":"41","Owner":"Peach","OwnerId":40,"Name":"FAF"},{"Value":"1-20","Owner":"Peach","OwnerId":40,"Name":"INTANGIBLE"}],"Game":"Smash4","Related":{"Smash4":{"Character":"http://api.kuroganehammer.com/api/characters/name/Peach?game=smash4","Self":"http://api.kuroganehammer.com/api/characterattributes/49ce73a38afc44aaadf5aa73439e4f60?game=smash4"},"Ultimate":{"Character":"http://api.kuroganehammer.com/api/characters/name/Peach?game=ultimate"}},"Links":[{"Rel":"self","Href":"http://api.kuroganehammer.com/api/characterattributes/49ce73a38afc44aaadf5aa73439e4f60?game=smash4"},{"Rel":"character","Href":"http://api.kuroganehammer.com/api/characters/name/Peach?game=smash4"}]},{"InstanceId":"4fa8a98848884a13b4df73f8f9763a9d","Name":"Tech Roll Backward","OwnerId":40,"Owner":"Peach","Values":[{"Value":"41","Owner":"Peach","OwnerId":40,"Name":"FAF"},{"Value":"1-20","Owner":"Peach","OwnerId":40,"Name":"INTANGIBLE"}],"Game":"Smash4","Related":{"Smash4":{"Character":"http://api.kuroganehammer.com/api/characters/name/Peach?game=smash4","Self":"http://api.kuroganehammer.com/api/characterattributes/4fa8a98848884a13b4df73f8f9763a9d?game=smash4"},"Ultimate":{"Character":"http://api.kuroganehammer.com/api/characters/name/Peach?game=ultimate"}},"Links":[{"Rel":"self","Href":"http://api.kuroganehammer.com/api/characterattributes/4fa8a98848884a13b4df73f8f9763a9d?game=smash4"},{"Rel":"character","Href":"http://api.kuroganehammer.com/api/characters/name/Peach?game=smash4"}]},{"InstanceId":"3925fe01d4554c828394086c72458e93","Name":"LedgeAttack","OwnerId":40,"Owner":"Peach","Values":[{"Value":"18-20 (Intangible: 1-15)","Owner":"Peach","OwnerId":40,"Name":"HITBOX ACTIVE"},{"Value":"56","Owner":"Peach","OwnerId":40,"Name":"FAF"},{"Value":"7","Owner":"Peach","OwnerId":40,"Name":"DAMAGE"}],"Game":"Smash4","Related":{"Smash4":{"Character":"http://api.kuroganehammer.com/api/characters/name/Peach?game=smash4","Self":"http://api.kuroganehammer.com/api/characterattributes/3925fe01d4554c828394086c72458e93?game=smash4"},"Ultimate":{"Character":"http://api.kuroganehammer.com/api/characters/name/Peach?game=ultimate"}},"Links":[{"Rel":"self","Href":"http://api.kuroganehammer.com/api/characterattributes/3925fe01d4554c828394086c72458e93?game=smash4"},{"Rel":"character","Href":"http://api.kuroganehammer.com/api/characters/name/Peach?game=smash4"}]},{"InstanceId":"dfab1f21c38b4bc3a6b60814291acb7f","Name":"LedgeGetUp","OwnerId":40,"Owner":"Peach","Values":[{"Value":"1-31","Owner":"Peach","OwnerId":40,"Name":"INTANGIBILITY"},{"Value":"33","Owner":"Peach","OwnerId":40,"Name":"FAF"}],"Game":"Smash4","Related":{"Smash4":{"Character":"http://api.kuroganehammer.com/api/characters/name/Peach?game=smash4","Self":"http://api.kuroganehammer.com/api/characterattributes/dfab1f21c38b4bc3a6b60814291acb7f?game=smash4"},"Ultimate":{"Character":"http://api.kuroganehammer.com/api/characters/name/Peach?game=ultimate"}},"Links":[{"Rel":"self","Href":"http://api.kuroganehammer.com/api/characterattributes/dfab1f21c38b4bc3a6b60814291acb7f?game=smash4"},{"Rel":"character","Href":"http://api.kuroganehammer.com/api/characters/name/Peach?game=smash4"}]},{"InstanceId":"c05047c8c83b47e5a9232d28da6f7342","Name":"LedgeRoll","OwnerId":40,"Owner":"Peach","Values":[{"Value":"1-28","Owner":"Peach","OwnerId":40,"Name":"INTANGIBILITY"},{"Value":"50","Owner":"Peach","OwnerId":40,"Name":"FAF"}],"Game":"Smash4","Related":{"Smash4":{"Character":"http://api.kuroganehammer.com/api/characters/name/Peach?game=smash4","Self":"http://api.kuroganehammer.com/api/characterattributes/c05047c8c83b47e5a9232d28da6f7342?game=smash4"},"Ultimate":{"Character":"http://api.kuroganehammer.com/api/characters/name/Peach?game=ultimate"}},"Links":[{"Rel":"self","Href":"http://api.kuroganehammer.com/api/characterattributes/c05047c8c83b47e5a9232d28da6f7342?game=smash4"},{"Rel":"character","Href":"http://api.kuroganehammer.com/api/characters/name/Peach?game=smash4"}]},{"InstanceId":"2a42a60ea55b402a90bf3dfd9973ab20","Name":"Jab Lock Front","OwnerId":40,"Owner":"Peach","Values":[{"Value":"26","Owner":"Peach","OwnerId":40,"Name":"JAB LOCK WINDOW"}],"Game":"Smash4","Related":{"Smash4":{"Character":"http://api.kuroganehammer.com/api/characters/name/Peach?game=smash4","Self":"http://api.kuroganehammer.com/api/characterattributes/2a42a60ea55b402a90bf3dfd9973ab20?game=smash4"},"Ultimate":{"Character":"http://api.kuroganehammer.com/api/characters/name/Peach?game=ultimate"}},"Links":[{"Rel":"self","Href":"http://api.kuroganehammer.com/api/characterattributes/2a42a60ea55b402a90bf3dfd9973ab20?game=smash4"},{"Rel":"character","Href":"http://api.kuroganehammer.com/api/characters/name/Peach?game=smash4"}]},{"InstanceId":"17d1179996e04d9f915f4a52ba949c36","Name":"Jab Lock Back","OwnerId":40,"Owner":"Peach","Values":[{"Value":"26","Owner":"Peach","OwnerId":40,"Name":"JAB LOCK WINDOW"}],"Game":"Smash4","Related":{"Smash4":{"Character":"http://api.kuroganehammer.com/api/characters/name/Peach?game=smash4","Self":"http://api.kuroganehammer.com/api/characterattributes/17d1179996e04d9f915f4a52ba949c36?game=smash4"},"Ultimate":{"Character":"http://api.kuroganehammer.com/api/characters/name/Peach?game=ultimate"}},"Links":[{"Rel":"self","Href":"http://api.kuroganehammer.com/api/characterattributes/17d1179996e04d9f915f4a52ba949c36?game=smash4"},{"Rel":"character","Href":"http://api.kuroganehammer.com/api/characters/name/Peach?game=smash4"}]},{"InstanceId":"4bb563c936434f698a50e48e3fe2f65c","Name":"LedgeJump","OwnerId":40,"Owner":"Peach","Values":[{"Value":"1-12","Owner":"Peach","OwnerId":40,"Name":"INTANGIBILITY"},{"Value":"13","Owner":"Peach","OwnerId":40,"Name":"FAF"}],"Game":"Smash4","Related":{"Smash4":{"Character":"http://api.kuroganehammer.com/api/characters/name/Peach?game=smash4","Self":"http://api.kuroganehammer.com/api/characterattributes/4bb563c936434f698a50e48e3fe2f65c?game=smash4"},"Ultimate":{"Character":"http://api.kuroganehammer.com/api/characters/name/Peach?game=ultimate"}},"Links":[{"Rel":"self","Href":"http://api.kuroganehammer.com/api/characterattributes/4bb563c936434f698a50e48e3fe2f65c?game=smash4"},{"Rel":"character","Href":"http://api.kuroganehammer.com/api/characters/name/Peach?game=smash4"}]},{"InstanceId":"1460eea84b724c0bb1dff99aa7d79e90","Name":"WalkSpeed","OwnerId":40,"Owner":"Peach","Values":[{"Value":"0.86","Owner":"Peach","OwnerId":40,"Name":"MAX WALK SPEED VALUE"}],"Game":"Smash4","Related":{"Smash4":{"Character":"http://api.kuroganehammer.com/api/characters/name/Peach?game=smash4","Self":"http://api.kuroganehammer.com/api/characterattributes/1460eea84b724c0bb1dff99aa7d79e90?game=smash4"},"Ultimate":{"Character":"http://api.kuroganehammer.com/api/characters/name/Peach?game=ultimate"}},"Links":[{"Rel":"self","Href":"http://api.kuroganehammer.com/api/characterattributes/1460eea84b724c0bb1dff99aa7d79e90?game=smash4"},{"Rel":"character","Href":"http://api.kuroganehammer.com/api/characters/name/Peach?game=smash4"}]},{"InstanceId":"c4d5e3c2806b4471b62e7b156ebae991","Name":"Weight","OwnerId":40,"Owner":"Peach","Values":[{"Value":"89","Owner":"Peach","OwnerId":40,"Name":"WEIGHT VALUE"}],"Game":"Smash4","Related":{"Smash4":{"Character":"http://api.kuroganehammer.com/api/characters/name/Peach?game=smash4","Self":"http://api.kuroganehammer.com/api/characterattributes/c4d5e3c2806b4471b62e7b156ebae991?game=smash4"},"Ultimate":{"Character":"http://api.kuroganehammer.com/api/characters/name/Peach?game=ultimate"}},"Links":[{"Rel":"self","Href":"http://api.kuroganehammer.com/api/characterattributes/c4d5e3c2806b4471b62e7b156ebae991?game=smash4"},{"Rel":"character","Href":"http://api.kuroganehammer.com/api/characters/name/Peach?game=smash4"}]}]