[{"InstanceId":"d9ab7ccab0d64f5a85ad0add0f41666d","Name":"AerialJump","OwnerId":44,"Owner":"Robin","Values":[{"Value":"33.208813","Owner":"Robin","OwnerId":44,"Name":"HEIGHT"}],"Game":"Smash4","Related":{"Smash4":{"Character":"http://api.kuroganehammer.com/api/characters/name/Robin?game=smash4","Self":"http://api.kuroganehammer.com/api/characterattributes/d9ab7ccab0d64f5a85ad0add0f41666d?game=smash4"},"Ultimate":{"Character":"http://api.kuroganehammer.com/api/characters/name/Robin?game=ultimate"}},"Links":[{"Rel":"self","Href":"http://api.kuroganehammer.com/api/characterattributes/d9ab7ccab0d64f5a85ad0add0f41666d?game=smash4"},{"Rel":"character","Href":"http://api.kuroganehammer.com/api/characters/name/Robin?game=smash4"}]},{"InstanceId":"846ab05a46294abd9202e56bae5604cc","Name":"AirAcceleration","OwnerId":44,"Owner":"Robin","Values":[{"Value":"0.07","Owner":"Robin","OwnerId":44,"Name":"MAX ADDITIONAL"},{"Value":"0.01","Owner":"Robin","OwnerId":44,"Name":"BASE VALUE"},{"Value":"0.08","Owner":"Robin","OwnerId":44,"Name":"TOTAL"}],"Game":"Smash4","Related":{"Smash4":{"Character":"http://api.kuroganehammer.com/api/characters/name/Robin?game=smash4","Self":"http://api.kuroganehammer.com/api/characterattributes/846ab05a46294abd9202e56bae5604cc?game=smash4"},"Ultimate":{"Character":"http://api.kuroganehammer.com/api/characters/name/Robin?game=ultimate"}},"Links":[{"Rel":"self","Href":"http://api.kuroganehammer.com/api/characterattributes/846ab05a46294abd9202e56bae5604cc?game=smash4"},{"Rel":"character","Href":"http://api.kuroganehammer.com/api/characters/name/Robin?game=smash4"}]},{"InstanceId":"10e83c50bbb74224a54b016c10d1bb60","Name":"AirDodge","OwnerId":44,"Owner":"Robin","Values":[{"Value":"3-28","Owner":"Robin","OwnerId":44,"Name":"INTANGIBLE"},{"Value":"34","Owner":"Robin","OwnerId":44,"Name":"FAF"}],"Game":"Smash4","Related":{"Smash4":{"Character":"http://api.kuroganehammer.com/api/characters/name/Robin?game=smash4","Self":"http://api.kuroganehammer.com/api/characterattributes/10e83c50bbb74224a54b016c10d1bb60?game=smash4"},"Ultimate":{"Character":"http://api.kuroganehammer.com/api/characters/name/Robin?game=ultimate"}},"Links":[{"Rel":"self","Href":"http://api.kuroganehammer.com/api/characterattributes/10e83c50bbb74224a54b016c10d1bb60?game=smash4"},{"Rel":"character","Href":"http://api.kuroganehammer.com/api/characters/name/Robin?game=smash4"}]},{"InstanceId":"dba208ebe0104b75814858b603272967","Name":"AirFriction","OwnerId":44,"Owner":"Robin","Values":[{"Value":"0.007","Owner":"Robin","OwnerId":44,"Name":"VALUE"}],"Game":"Smash4","Related":{"Smash4":{"Character":"http://api.kuroganehammer.com/api/characters/name/Robin?game=smash4","Self":"http://api.kuroganehammer.com/api/characterattributes/dba208ebe0104b75814858b603272967?game=smash4"},"Ultimate":{"Character":"http://api.kuroganehammer.com/api/characters/name/Robin?game=ultimate"}},"Links":[{"Rel":"self","Href":"http://api.kuroganehammer.com/api/characterattributes/dba208ebe0104b75814858b603272967?game=smash4"},{"Rel":"character","Href":"http://api.kuroganehammer.com/api/characters/name/Robin?game=smash4"}]},{"InstanceId":"20e7d324e7f7401caf41031a55eca06a","Name":"AirSpeed","OwnerId":44,"Owner":"Robin","Values":[{"Value":"1","Owner":"Robin","OwnerId":44,"Name":"MAX AIR SPEED VALUE"}],"Game":"Smash4","Related":{"Smash4":{"Character":"http://api.kuroganehammer.com/api/characters/name/Robin?game=smash4","Self":"http://api.kuroganehammer.com/api/characterattributes/20e7d324e7f7401caf41031a55eca06a?game=smash4"},"Ultimate":{"Character":"http://api.kuroganehammer.com/api/characters/name/Robin?game=ultimate"}},"Links":[{"Rel":"self","Href":"http://api.kuroganehammer.com/api/characterattributes/20e7d324e7f7401caf41031a55eca06a?game=smash4"},{"Rel":"character","Href":"http://api.kuroganehammer.com/api/characters/name/Robin?game=smash4"}]},{"InstanceId":"1ff12d16a12b4991a7d1c0bb4b5d224e","Name":"FallSpeed","OwnerId":44,"Owner":"Robin","Values":[{"Value":"1.5","Owner":"Robin","OwnerId":44,"Name":"MAX FALL SPEED"},{"Value":"2.4","Owner":"Robin","OwnerId":44,"Name":"FAST FALL SPEED"},{"Value":"60%","Owner":"Robin","OwnerId":44,"Name":"SPEED INCREASE"}],"Game":"Smash4","Related":{"Smash4":{"Character":"http://api.kuroganehammer.com/api/characters/name/Robin?game=smash4","Self":"http://api.kuroganehammer.com/api/characterattributes/1ff12d16a12b4991a7d1c0bb4b5d224e?game=smash4"},"Ultimate":{"Character":"http://api.kuroganehammer.com/api/characters/name/Robin?game=ultimate"}},"Links":[{"Rel":"self","Href":"http://api.kuroganehammer.com/api/characterattributes/1ff12d16a12b4991a7d1c0bb4b5d224e?game=smash4"},{"Rel":"character","Href":"http://api.kuroganehammer.com/api/characters/name/Robin?game=smash4"}]},{"InstanceId":"db6c36e713774d2e8bb82755c14ee6e6","Name":"FullHop","OwnerId":44,"Owner":"Robin","Values":[{"Value":"33.208813","Owner":"Robin","OwnerId":44,"Name":"HEIGHT"}],"Game":"Smash4","Related":{"Smash4":{"Character":"http://api.kuroganehammer.com/api/characters/name/Robin?game=smash4","Self":"http://api.kuroganehammer.com/api/characterattributes/db6c36e713774d2e8bb82755c14ee6e6?game=smash4"},"Ultimate":{"Character":"http://api.kuroganehammer.com/api/characters/name/Robin?game=ultimate"}},"Links":[{"Rel":"self","Href":"http://api.kuroganehammer.com/api/characterattributes/db6c36e713774d2e8bb82755c14ee6e6?game=smash4"},{"Rel":"character","Href":"http://api.kuroganehammer.com/api/characters/name/Robin?game=smash4"}]},{"InstanceId":"934480dc6e8347e3b86595307931088f","Name":"Gravity","OwnerId":44,"Owner":"Robin","Values":[{"Value":"0.089","Owner":"Robin","OwnerId":44,"Name":"VALUE"}],"Game":"Smash4","Related":{"Smash4":{"Character":"http://api.kuroganehammer.com/api/characters/name/Robin?game=smash4","Self":"http://api.kuroganehammer.com/api/characterattributes/934480dc6e8347e3b86595307931088f?game=smash4"},"Ultimate":{"Character":"http://api.kuroganehammer.com/api/characters/name/Robin?game=ultimate"}},"Links":[{"Rel":"self","Href":"http://api.kuroganehammer.com/api/characterattributes/934480dc6e8347e3b86595307931088f?game=smash4"},{"Rel":"character","Href":"http://api.kuroganehammer.com/api/characters/name/Robin?game=smash4"}]},{"InstanceId":"75abde9ccf284494b8bc95cc6e2514ad","Name":"JumpSquat","OwnerId":44,"Owner":"Robin","Values":[{"Value":"7","Owner":"Robin","OwnerId":44,"Name":"VALUE"}],"Game":"Smash4","Related":{"Smash4":{"Character":"http://api.kuroganehammer.com/api/characters/name/Robin?game=smash4","Self":"http://api.kuroganehammer.com/api/characterattributes/75abde9ccf284494b8bc95cc6e2514ad?game=smash4"},"Ultimate":{"Character":"http://api.kuroganehammer.com/api/characters/name/Robin?game=ultimate"}},"Links":[{"Rel":"self","Href":"http://api.kuroganehammer.com/api/characterattributes/75abde9ccf284494b8bc95cc6e2514ad?game=smash4"},{"Rel":"character","Href":"http://api.kuroganehammer.com/api/characters/name/Robin?game=smash4"}]},{"InstanceId":"47ebf5ada0354ad7b4f81529e473c82c","Name":"LedgeHop","OwnerId":44,"Owner":"Robin","Values":[{"Value":"36.604404","Owner":"Robin","OwnerId":44,"Name":"HEIGHT"}],"Game":"Smash4","Related":{"Smash4":{"Character":"http://api.kuroganehammer.com/api/characters/name/Robin?game=smash4","Self":"http://api.kuroganehammer.com/api/characterattributes/47ebf5ada0354ad7b4f81529e473c82c?game=smash4"},"Ultimate":{"Character":"http://api.kuroganehammer.com/api/characters/name/Robin?game=ultimate"}},"Links":[{"Rel":"self","Href":"http://api.kuroganehammer.com/api/characterattributes/47ebf5ada0354ad7b4f81529e473c82c?game=smash4"},{"Rel":"character","Href":"http://api.kuroganehammer.com/api/characters/name/Robin?game=smash4"}]},{"InstanceId":"0e7f4dd6df184761a59cfcdc0d318926","Name":"Rolls","OwnerId":44,"Owner":"Robin","Values":[{"Value":"4-18","Owner":"Robin","OwnerId":44,"Name":"INTANGIBLE"},{"Value":"33","Owner":"Robin","OwnerId":44,"Name":"FAF"}],"Game":"Smash4","Related":{"Smash4":{"Character":"http://api.kuroganehammer.com/api/characters/name/Robin?game=smash4","Self":"http://api.kuroganehammer.com/api/characterattributes/0e7f4dd6df184761a59cfcdc0d318926?game=smash4"},"Ultimate":{"Character":"http://api.kuroganehammer.com/api/characters/name/Robin?game=ultimate"}},"Links":[{"Rel":"self","Href":"http://api.kuroganehammer.com/api/characterattributes/0e7f4dd6df184761a59cfcdc0d318926?game=smash4"},{"Rel":"character","Href":"http://api.kuroganehammer.com/api/characters/name/Robin?game=smash4"}]},{"InstanceId":"646ba210daed4f938b380e369b7f2ba7","Name":"RunSpeed","OwnerId":44,"Owner":"Robin","Values":[{"Value":"1.15","Owner":"Robin","OwnerId":44,"Name":"MAX RUN SPEED VALUE"}],"Game":"Smash4","Related":{"Smash4":{"Character":"http://api.kuroganehammer.com/api/characters/name/Robin?game=smash4","Self":"http://api.kuroganehammer.com/api/characterattributes/646ba210daed4f938b380e369b7f2ba7?game=smash4"},"Ultimate":{"Character":"http://api.kuroganehammer.com/api/characters/name/Robin?game=ultimate"}},"Links":[{"Rel":"self","Href":"http://api.kuroganehammer.com/api/characterattributes/646ba210daed4f938b380e369b7f2ba7?game=smash4"},{"Rel":"character","Href":"http://api.kuroganehammer.com/api/characters/name/Robin?game=smash4"}]},{"InstanceId":"ec36eefa93844ca3a4712fe04a63dc16","Name":"ShieldSize","OwnerId":44,"Owner":"Robin","Values":[{"Value":"11.235","Owner":"Robin","OwnerId":44,"Name":"SIZE"}],"Game":"Smash4","Related":{"Smash4":{"Character":"http://api.kuroganehammer.com/api/characters/name/Robin?game=smash4","Self":"http://api.kuroganehammer.com/api/characterattributes/ec36eefa93844ca3a4712fe04a63dc16?game=smash4"},"Ultimate":{"Character":"http://api.kuroganehammer.com/api/characters/name/Robin?game=ultimate"}},"Links":[{"Rel":"self","Href":"http://api.kuroganehammer.com/api/characterattributes/ec36eefa93844ca3a4712fe04a63dc16?game=smash4"},{"Rel":"character","Href":"http://api.kuroganehammer.com/api/characters/name/Robin?game=smash4"}]},{"InstanceId":"64185b575a7f497588d00e0d1aa15b2f","Name":"ShortHop","OwnerId":44,"Owner":"Robin","Values":[{"Value":"16.018034","Owner":"Robin","OwnerId":44,"Name":"HEIGHT"}],"Game":"Smash4","Related":{"Smash4":{"Character":"http://api.kuroganehammer.com/api/characters/name/Robin?game=smash4","Self":"http://api.kuroganehammer.com/api/characterattributes/64185b575a7f497588d00e0d1aa15b2f?game=smash4"},"Ultimate":{"Character":"http://api.kuroganehammer.com/api/characters/name/Robin?game=ultimate"}},"Links":[{"Rel":"self","Href":"http://api.kuroganehammer.com/api/characterattributes/64185b575a7f497588d00e0d1aa15b2f?game=smash4"},{"Rel":"character","Href":"http://api.kuroganehammer.com/api/characters/name/Robin?game=smash4"}]},{"InstanceId":"31a92da4565a40a087ccb0a464dfa9da","Name":"HardTrip","OwnerId":44,"Owner":"Robin","Values":[{"Value":"41","Owner":"Robin","OwnerId":44,"Name":"FAF"},{"Value":"1-5","Owner":"Robin","OwnerId":44,"Name":"INTANGIBLE"}],"Game":"Smash4","Related":{"Smash4":{"Character":"http://api.kuroganehammer.com/api/characters/name/Robin?game=smash4","Self":"http://api.kuroganehammer.com/api/characterattributes/31a92da4565a40a087ccb0a464dfa9da?game=smash4"},"Ultimate":{"Character":"http://api.kuroganehammer.com/api/characters/name/Robin?game=ultimate"}},"Links":[{"Rel":"self","Href":"http://api.kuroganehammer.com/api/characterattributes/31a92da4565a40a087ccb0a464dfa9da?game=smash4"},{"Rel":"character","Href":"http://api.kuroganehammer.com/api/characters/name/Robin?game=smash4"}]},{"InstanceId":"4b136ae08ab04302b403487b12f71c31","Name":"SoftTrip","OwnerId":44,"Owner":"Robin","Values":[{"Value":"30","Owner":"Robin","OwnerId":44,"Name":"FAF"},{"Value":"1-5","Owner":"Robin","OwnerId":44,"Name":"INTANGIBLE"}],"Game":"Smash4","Related":{"Smash4":{"Character":"http://api.kuroganehammer.com/api/characters/name/Robin?game=smash4","Self":"http://api.kuroganehammer.com/api/characterattributes/4b136ae08ab04302b403487b12f71c31?game=smash4"},"Ultimate":{"Character":"http://api.kuroganehammer.com/api/characters/name/Robin?game=ultimate"}},"Links":[{"Rel":"self","Href":"http://api.kuroganehammer.com/api/characterattributes/4b136ae08ab04302b403487b12f71c31?game=smash4"},{"Rel":"character","Href":"http://api.kuroganehammer.com/api/characters/name/Robin?game=smash4"}]},{"InstanceId":"f77c68f69fce4420aa43464a02f3161b","Name":"Spotdodge","OwnerId":44,"Owner":"Robin","Values":[{"Value":"3-18","Owner":"Robin","OwnerId":44,"Name":"INTANGIBLE"},{"Value":"28","Owner":"Robin","OwnerId":44,"Name":"FAF"}],"Game":"Smash4","Related":{"Smash4":{"Character":"http://api.kuroganehammer.com/api/characters/name/Robin?game=smash4","Self":"http://api.kuroganehammer.com/api/characterattributes/f77c68f69fce4420aa43464a02f3161b?game=smash4"},"Ultimate":{"Character":"http://api.kuroganehammer.com/api/characters/name/Robin?game=ultimate"}},"Links":[{"Rel":"self","Href":"http://api.kuroganehammer.com/api/characterattributes/f77c68f69fce4420aa43464a02f3161b?game=smash4"},{"Rel":"character","Href":"http://api.kuroganehammer.com/api/characters/name/Robin?game=smash4"}]},{"InstanceId":"ed819ffdc0b24970b0eba452ad906216","Name":"Traction","OwnerId":44,"Owner":"Robin","Values":[{"Value":"0.055","Owner":"Robin","OwnerId":44,"Name":"VALUE"}],"Game":"Smash4","Related":{"Smash4":{"Character":"http://api.kuroganehammer.com/api/characters/name/Robin?game=smash4","Self":"http://api.kuroganehammer.com/api/characterattributes/ed819ffdc0b24970b0eba452ad906216?game=smash4"},"Ultimate":{"Character":"http://api.kuroganehammer.com/api/characters/name/Robin?game=ultimate"}},"Links":[{"Rel":"self","Href":"http://api.kuroganehammer.com/api/characterattributes/ed819ffdc0b24970b0eba452ad906216?game=smash4"},{"Rel":"character","Href":"http://api.kuroganehammer.com/api/characters/name/Robin?game=smash4"}]},{"InstanceId":"496d27080bf84135a3cb6074f699dbba","Name":"GetUp On Back","OwnerId":44,"Owner":"Robin","Values":[{"Value":"30","Owner":"Robin","OwnerId":44,"Name":"FAF"},{"Value":"1-22","Owner":"Robin","OwnerId":44,"Name":"INTANGIBLE"}],"Game":"Smash4","Related":{"Smash4":{"Character":"http://api.kuroganehammer.com/api/characters/name/Robin?game=smash4","Self":"http://api.kuroganehammer.com/api/characterattributes/496d27080bf84135a3cb6074f699dbba?game=smash4"},"Ultimate":{"Character":"http://api.kuroganehammer.com/api/characters/name/Robin?game=ultimate"}},"Links":[{"Rel":"self","Href":"http://api.kuroganehammer.com/api/characterattributes/496d27080bf84135a3cb6074f699dbba?game=smash4"},{"Rel":"character","Href":"http://api.kuroganehammer.com/api/characters/name/Robin?game=smash4"}]},{"InstanceId":"9b240d5c54d24666850314cc38d7a13c","Name":"GetUp On Front","OwnerId":44,"Owner":"Robin","Values":[{"Value":"30","Owner":"Robin","OwnerId":44,"Name":"FAF"},{"Value":"1-22","Owner":"Robin","OwnerId":44,"Name":"INTANGIBLE"}],"Game":"Smash4","Related":{"Smash4":{"Character":"http://api.kuroganehammer.com/api/characters/name/Robin?game=smash4","Self":"http://api.kuroganehammer.com/api/characterattributes/9b240d5c54d24666850314cc38d7a13c?game=smash4"},"Ultimate":{"Character":"http://api.kuroganehammer.com/api/characters/name/Robin?game=ultimate"}},"Links":[{"Rel":"self","Href":"http://api.kuroganehammer.com/api/characterattributes/9b240d5c54d24666850314cc38d7a13c?game=smash4"},{"Rel":"character","Href":"http://api.kuroganehammer.com/api/characters/name/Robin?game=smash4"}]},{"InstanceId":"2df4375db219444e8d681babe0987377","Name":"GetUp Back Roll Back","OwnerId":44,"Owner":"Robin","Values":[{"Value":"1-19","Owner":"Robin","OwnerId":44,"Name":"INTANGIBLE"},{"Value":"36","Owner":"Robin","OwnerId":44,"Name":"FAF"}],"Game":"Smash4","Related":{"Smash4":{"Character":"http://api.kuroganehammer.com/api/characters/name/Robin?game=smash4","Self":"http://api.kuroganehammer.com/api/characterattributes/2df4375db219444e8d681babe0987377?game=smash4"},"Ultimate":{"Character":"http://api.kuroganehammer.com/api/characters/name/Robin?game=ultimate"}},"Links":[{"Rel":"self","Href":"http://api.kuroganehammer.com/api/characterattributes/2df4375db219444e8d681babe0987377?game=smash4"},{"Rel":"character","Href":"http://api.kuroganehammer.com/api/characters/name/Robin?game=smash4"}]},{"InstanceId":"6c08bc34c5e14ff1b03ba5b8cd7cd208","Name":"GetUp Back Roll Front","OwnerId":44,"Owner":"Robin","Values":[{"Value":"1-19","Owner":"Robin","OwnerId":44,"Name":"INTANGIBLE"},{"Value":"36","Owner":"Robin","OwnerId":44,"Name":"FAF"}],"Game":"Smash4","Related":{"Smash4":{"Character":"http://api.kuroganehammer.com/api/characters/name/Robin?game=smash4","Self":"http://api.kuroganehammer.com/api/characterattributes/6c08bc34c5e14ff1b03ba5b8cd7cd208?game=smash4"},"Ultimate":{"Character":"http://api.kuroganehammer.com/api/characters/name/Robin?game=ultimate"}},"Links":[{"Rel":"self","Href":"http://api.kuroganehammer.com/api/characterattributes/6c08bc34c5e14ff1b03ba5b8cd7cd208?game=smash4"},{"Rel":"character","Href":"http://api.kuroganehammer.com/api/characters/name/Robin?game=smash4"}]},{"InstanceId":"ce95a318f7044cbfb111b62bbfa391b9","Name":"GetUp Forward Roll Back","OwnerId":44,"Owner":"Robin","Values":[{"Value":"1-19","Owner":"Robin","OwnerId":44,"Name":"INTANGIBLE"},{"Value":"36","Owner":"Robin","OwnerId":44,"Name":"FAF"}],"Game":"Smash4","Related":{"Smash4":{"Character":"http://api.kuroganehammer.com/api/characters/name/Robin?game=smash4","Self":"http://api.kuroganehammer.com/api/characterattributes/ce95a318f7044cbfb111b62bbfa391b9?game=smash4"},"Ultimate":{"Character":"http://api.kuroganehammer.com/api/characters/name/Robin?game=ultimate"}},"Links":[{"Rel":"self","Href":"http://api.kuroganehammer.com/api/characterattributes/ce95a318f7044cbfb111b62bbfa391b9?game=smash4"},{"Rel":"character","Href":"http://api.kuroganehammer.com/api/characters/name/Robin?game=smash4"}]},{"InstanceId":"a9cf0a7a7d0b43d0819f325144ea9010","Name":"GetUp Forward Roll Front","OwnerId":44,"Owner":"Robin","Values":[{"Value":"1-19","Owner":"Robin","OwnerId":44,"Name":"INTANGIBLE"},{"Value":"36","Owner":"Robin","OwnerId":44,"Name":"FAF"}],"Game":"Smash4","Related":{"Smash4":{"Character":"http://api.kuroganehammer.com/api/characters/name/Robin?game=smash4","Self":"http://api.kuroganehammer.com/api/characterattributes/a9cf0a7a7d0b43d0819f325144ea9010?game=smash4"},"Ultimate":{"Character":"http://api.kuroganehammer.com/api/characters/name/Robin?game=ultimate"}},"Links":[{"Rel":"self","Href":"http://api.kuroganehammer.com/api/characterattributes/a9cf0a7a7d0b43d0819f325144ea9010?game=smash4"},{"Rel":"character","Href":"http://api.kuroganehammer.com/api/characters/name/Robin?game=smash4"}]},{"InstanceId":"5a96f0c699eb4547bf59206fb6b49de2","Name":"Tech Frame Data","OwnerId":44,"Owner":"Robin","Values":[{"Value":"27","Owner":"Robin","OwnerId":44,"Name":"FAF"},{"Value":"1-20","Owner":"Robin","OwnerId":44,"Name":"INTANGIBLE"}],"Game":"Smash4","Related":{"Smash4":{"Character":"http://api.kuroganehammer.com/api/characters/name/Robin?game=smash4","Self":"http://api.kuroganehammer.com/api/characterattributes/5a96f0c699eb4547bf59206fb6b49de2?game=smash4"},"Ultimate":{"Character":"http://api.kuroganehammer.com/api/characters/name/Robin?game=ultimate"}},"Links":[{"Rel":"self","Href":"http://api.kuroganehammer.com/api/characterattributes/5a96f0c699eb4547bf59206fb6b49de2?game=smash4"},{"Rel":"character","Href":"http://api.kuroganehammer.com/api/characters/name/Robin?game=smash4"}]},{"InstanceId":"da96b9899c9c420dacf6b67ead0bb7bc","Name":"Tech Roll Forward","OwnerId":44,"Owner":"Robin","Values":[{"Value":"41","Owner":"Robin","OwnerId":44,"Name":"FAF"},{"Value":"1-20","Owner":"Robin","OwnerId":44,"Name":"INTANGIBLE"}],"Game":"Smash4","Related":{"Smash4":{"Character":"http://api.kuroganehammer.com/api/characters/name/Robin?game=smash4","Self":"http://api.kuroganehammer.com/api/characterattributes/da96b9899c9c420dacf6b67ead0bb7bc?game=smash4"},"Ultimate":{"Character":"http://api.kuroganehammer.com/api/characters/name/Robin?game=ultimate"}},"Links":[{"Rel":"self","Href":"http://api.kuroganehammer.com/api/characterattributes/da96b9899c9c420dacf6b67ead0bb7bc?game=smash4"},{"Rel":"character","Href":"http://api.kuroganehammer.com/api/characters/name/Robin?game=smash4"}]},{"InstanceId":"bca6f55f65aa49d9ba6ae3feeed40240","Name":"Tech Roll Backward","OwnerId":44,"Owner":"Robin","Values":[{"Value":"41","Owner":"Robin","OwnerId":44,"Name":"FAF"},{"Value":"1-20","Owner":"Robin","OwnerId":44,"Name":"INTANGIBLE"}],"Game":"Smash4","Related":{"Smash4":{"Character":"http://api.kuroganehammer.com/api/characters/name/Robin?game=smash4","Self":"http://api.kuroganehammer.com/api/characterattributes/bca6f55f65aa49d9ba6ae3feeed40240?game=smash4"},"Ultimate":{"Character":"http://api.kuroganehammer.com/api/characters/name/Robin?game=ultimate"}},"Links":[{"Rel":"self","Href":"http://api.kuroganehammer.com/api/characterattributes/bca6f55f65aa49d9ba6ae3feeed40240?game=smash4"},{"Rel":"character","Href":"http://api.kuroganehammer.com/api/characters/name/Robin?game=smash4"}]},{"InstanceId":"bf64aa8e5bd74e3595a7dba434c05f1a","Name":"LedgeAttack","OwnerId":44,"Owner":"Robin","Values":[{"Value":"25-27 (Intangible: 1-22)","Owner":"Robin","OwnerId":44,"Name":"HITBOX ACTIVE"},{"Value":"56","Owner":"Robin","OwnerId":44,"Name":"FAF"},{"Value":"7","Owner":"Robin","OwnerId":44,"Name":"DAMAGE"}],"Game":"Smash4","Related":{"Smash4":{"Character":"http://api.kuroganehammer.com/api/characters/name/Robin?game=smash4","Self":"http://api.kuroganehammer.com/api/characterattributes/bf64aa8e5bd74e3595a7dba434c05f1a?game=smash4"},"Ultimate":{"Character":"http://api.kuroganehammer.com/api/characters/name/Robin?game=ultimate"}},"Links":[{"Rel":"self","Href":"http://api.kuroganehammer.com/api/characterattributes/bf64aa8e5bd74e3595a7dba434c05f1a?game=smash4"},{"Rel":"character","Href":"http://api.kuroganehammer.com/api/characters/name/Robin?game=smash4"}]},{"InstanceId":"c45515d7a5364ca98c6fffbf050a6a18","Name":"LedgeGetUp","OwnerId":44,"Owner":"Robin","Values":[{"Value":"1-33","Owner":"Robin","OwnerId":44,"Name":"INTANGIBILITY"},{"Value":"35","Owner":"Robin","OwnerId":44,"Name":"FAF"}],"Game":"Smash4","Related":{"Smash4":{"Character":"http://api.kuroganehammer.com/api/characters/name/Robin?game=smash4","Self":"http://api.kuroganehammer.com/api/characterattributes/c45515d7a5364ca98c6fffbf050a6a18?game=smash4"},"Ultimate":{"Character":"http://api.kuroganehammer.com/api/characters/name/Robin?game=ultimate"}},"Links":[{"Rel":"self","Href":"http://api.kuroganehammer.com/api/characterattributes/c45515d7a5364ca98c6fffbf050a6a18?game=smash4"},{"Rel":"character","Href":"http://api.kuroganehammer.com/api/characters/name/Robin?game=smash4"}]},{"InstanceId":"49df94f6c8d040e4978d8da096dd278d","Name":"LedgeRoll","OwnerId":44,"Owner":"Robin","Values":[{"Value":"1-26","Owner":"Robin","OwnerId":44,"Name":"INTANGIBILITY"},{"Value":"50","Owner":"Robin","OwnerId":44,"Name":"FAF"}],"Game":"Smash4","Related":{"Smash4":{"Character":"http://api.kuroganehammer.com/api/characters/name/Robin?game=smash4","Self":"http://api.kuroganehammer.com/api/characterattributes/49df94f6c8d040e4978d8da096dd278d?game=smash4"},"Ultimate":{"Character":"http://api.kuroganehammer.com/api/characters/name/Robin?game=ultimate"}},"Links":[{"Rel":"self","Href":"http://api.kuroganehammer.com/api/characterattributes/49df94f6c8d040e4978d8da096dd278d?game=smash4"},{"Rel":"character","Href":"http://api.kuroganehammer.com/api/characters/name/Robin?game=smash4"}]},{"InstanceId":"09b577307a6d493bbc9581af6f3c2b95","Name":"Jab Lock Front","OwnerId":44,"Owner":"Robin","Values":[{"Value":"26","Owner":"Robin","OwnerId":44,"Name":"JAB LOCK WINDOW"}],"Game":"Smash4","Related":{"Smash4":{"Character":"http://api.kuroganehammer.com/api/characters/name/Robin?game=smash4","Self":"http://api.kuroganehammer.com/api/characterattributes/09b577307a6d493bbc9581af6f3c2b95?game=smash4"},"Ultimate":{"Character":"http://api.kuroganehammer.com/api/characters/name/Robin?game=ultimate"}},"Links":[{"Rel":"self","Href":"http://api.kuroganehammer.com/api/characterattributes/09b577307a6d493bbc9581af6f3c2b95?game=smash4"},{"Rel":"character","Href":"http://api.kuroganehammer.com/api/characters/name/Robin?game=smash4"}]},{"InstanceId":"114b8b6680414edb9018eaf432dc5f4d","Name":"Jab Lock Back","OwnerId":44,"Owner":"Robin","Values":[{"Value":"26","Owner":"Robin","OwnerId":44,"Name":"JAB LOCK WINDOW"}],"Game":"Smash4","Related":{"Smash4":{"Character":"http://api.kuroganehammer.com/api/characters/name/Robin?game=smash4","Self":"http://api.kuroganehammer.com/api/characterattributes/114b8b6680414edb9018eaf432dc5f4d?game=smash4"},"Ultimate":{"Character":"http://api.kuroganehammer.com/api/characters/name/Robin?game=ultimate"}},"Links":[{"Rel":"self","Href":"http://api.kuroganehammer.com/api/characterattributes/114b8b6680414edb9018eaf432dc5f4d?game=smash4"},{"Rel":"character","Href":"http://api.kuroganehammer.com/api/characters/name/Robin?game=smash4"}]},{"InstanceId":"7889abcef81b4dbca3ee6574ae7db9be","Name":"LedgeJump","OwnerId":44,"Owner":"Robin","Values":[{"Value":"1-12","Owner":"Robin","OwnerId":44,"Name":"INTANGIBILITY"},{"Value":"13","Owner":"Robin","OwnerId":44,"Name":"FAF"}],"Game":"Smash4","Related":{"Smash4":{"Character":"http://api.kuroganehammer.com/api/characters/name/Robin?game=smash4","Self":"http://api.kuroganehammer.com/api/characterattributes/7889abcef81b4dbca3ee6574ae7db9be?game=smash4"},"Ultimate":{"Character":"http://api.kuroganehammer.com/api/characters/name/Robin?game=ultimate"}},"Links":[{"Rel":"self","Href":"http://api.kuroganehammer.com/api/characterattributes/7889abcef81b4dbca3ee6574ae7db9be?game=smash4"},{"Rel":"character","Href":"http://api.kuroganehammer.com/api/characters/name/Robin?game=smash4"}]},{"InstanceId":"d72cf0f73361499d86d063760db1da0e","Name":"WalkSpeed","OwnerId":44,"Owner":"Robin","Values":[{"Value":"0.891","Owner":"Robin","OwnerId":44,"Name":"MAX WALK SPEED VALUE"}],"Game":"Smash4","Related":{"Smash4":{"Character":"http://api.kuroganehammer.com/api/characters/name/Robin?game=smash4","Self":"http://api.kuroganehammer.com/api/characterattributes/d72cf0f73361499d86d063760db1da0e?game=smash4"},"Ultimate":{"Character":"http://api.kuroganehammer.com/api/characters/name/Robin?game=ultimate"}},"Links":[{"Rel":"self","Href":"http://api.kuroganehammer.com/api/characterattributes/d72cf0f73361499d86d063760db1da0e?game=smash4"},{"Rel":"character","Href":"http://api.kuroganehammer.com/api/characters/name/Robin?game=smash4"}]},{"InstanceId":"9f96dca8933d4054927bf6a86de67cc3","Name":"Weight","OwnerId":44,"Owner":"Robin","Values":[{"Value":"95","Owner":"Robin","OwnerId":44,"Name":"WEIGHT VALUE"}],"Game":"Smash4","Related":{"Smash4":{"Character":"http://api.kuroganehammer.com/api/characters/name/Robin?game=smash4","Self":"http://api.kuroganehammer.com/api/characterattributes/9f96dca8933d4054927bf6a86de67cc3?game=smash4"},"Ultimate":{"Character":"http://api.kuroganehammer.com/api/characters/name/Robin?game=ultimate"}},"Links":[{"Rel":"self","Href":"http://api.kuroganehammer.com/api/characterattributes/9f96dca8933d4054927bf6a86de67cc3?game=smash4"},{"Rel":"character","Href":"http://api.kuroganehammer.com/api/characters/name/Robin?game=smash4"}]}]