[{"InstanceId":"4ea091f5a74448b48f0d3f21df2fcec1","Name":"Jab 1","OwnerId":38,"Owner":"PAC-MAN","HitboxActive":"4-6","FirstActionableFrame":"20","BaseDamage":"3","Angle":"80/361","BaseKnockBackSetKnockback":"W: 22/16","LandingLag":null,"AutoCancel":null,"KnockbackGrowth":"100","MoveType":"ground","IsWeightDependent":false,"Game":"Smash4","Related":{"Smash4":{"Character":"http://api.kuroganehammer.com/api/characters/name/PAC-MAN?game=smash4","Self":"http://api.kuroganehammer.com/api/moves/4ea091f5a74448b48f0d3f21df2fcec1?game=smash4"},"Ultimate":{"Character":"http://api.kuroganehammer.com/api/characters/name/PAC-MAN?game=ultimate"}},"Links":[{"Rel":"self","Href":"http://api.kuroganehammer.com/api/moves/4ea091f5a74448b48f0d3f21df2fcec1?game=smash4"},{"Rel":"character","Href":"http://api.kuroganehammer.com/api/characters/name/PAC-MAN?game=smash4"}]},{"InstanceId":"66ffe07342fc49b18011aefda7f0af70","Name":"Jab 2","OwnerId":38,"Owner":"PAC-MAN","HitboxActive":"4-6","FirstActionableFrame":"22","BaseDamage":"2","Angle":"80/361","BaseKnockBackSetKnockback":"W: 26/15","LandingLag":null,"AutoCancel":null,"KnockbackGrowth":"100","MoveType":"ground","IsWeightDependent":false,"Game":"Smash4","Related":{"Smash4":{"Character":"http://api.kuroganehammer.com/api/characters/name/PAC-MAN?game=smash4","Self":"http://api.kuroganehammer.com/api/moves/66ffe07342fc49b18011aefda7f0af70?game=smash4"},"Ultimate":{"Character":"http://api.kuroganehammer.com/api/characters/name/PAC-MAN?game=ultimate"}},"Links":[{"Rel":"self","Href":"http://api.kuroganehammer.com/api/moves/66ffe07342fc49b18011aefda7f0af70?game=smash4"},{"Rel":"character","Href":"http://api.kuroganehammer.com/api/characters/name/PAC-MAN?game=smash4"}]},{"InstanceId":"0aaeebb3986448839724dd0ef019a4c2","Name":"Jab 3","OwnerId":38,"Owner":"PAC-MAN","HitboxActive":"4-7","FirstActionableFrame":"34","BaseDamage":"4","Angle":"361","BaseKnockBackSetKnockback":"45","LandingLag":null,"AutoCancel":null,"KnockbackGrowth":"106","MoveType":"ground","IsWeightDependent":false,"Game":"Smash4","Related":{"Smash4":{"Character":"http://api.kuroganehammer.com/api/characters/name/PAC-MAN?game=smash4","Self":"http://api.kuroganehammer.com/api/moves/0aaeebb3986448839724dd0ef019a4c2?game=smash4"},"Ultimate":{"Character":"http://api.kuroganehammer.com/api/characters/name/PAC-MAN?game=ultimate"}},"Links":[{"Rel":"self","Href":"http://api.kuroganehammer.com/api/moves/0aaeebb3986448839724dd0ef019a4c2?game=smash4"},{"Rel":"character","Href":"http://api.kuroganehammer.com/api/characters/name/PAC-MAN?game=smash4"}]},{"InstanceId":"88783dbcba964cf0a13450f308dcf08d","Name":"Dash Attack (Windbox)","OwnerId":38,"Owner":"PAC-MAN","HitboxActive":"3-9","FirstActionableFrame":"42","BaseDamage":"0","Angle":"361","BaseKnockBackSetKnockback":"W: 12","LandingLag":null,"AutoCancel":null,"KnockbackGrowth":"100","MoveType":"ground","IsWeightDependent":false,"Game":"Smash4","Related":{"Smash4":{"Character":"http://api.kuroganehammer.com/api/characters/name/PAC-MAN?game=smash4","Self":"http://api.kuroganehammer.com/api/moves/88783dbcba964cf0a13450f308dcf08d?game=smash4"},"Ultimate":{"Character":"http://api.kuroganehammer.com/api/characters/name/PAC-MAN?game=ultimate"}},"Links":[{"Rel":"self","Href":"http://api.kuroganehammer.com/api/moves/88783dbcba964cf0a13450f308dcf08d?game=smash4"},{"Rel":"character","Href":"http://api.kuroganehammer.com/api/characters/name/PAC-MAN?game=smash4"}]},{"InstanceId":"ccce455573b0452394665585bc6b6816","Name":"Dash Attack (Hits 1-2)","OwnerId":38,"Owner":"PAC-MAN","HitboxActive":"10-11, 20-21","FirstActionableFrame":"-","BaseDamage":"2","Angle":"12","BaseKnockBackSetKnockback":"45","LandingLag":null,"AutoCancel":null,"KnockbackGrowth":"15","MoveType":"ground","IsWeightDependent":false,"Game":"Smash4","Related":{"Smash4":{"Character":"http://api.kuroganehammer.com/api/characters/name/PAC-MAN?game=smash4","Self":"http://api.kuroganehammer.com/api/moves/ccce455573b0452394665585bc6b6816?game=smash4"},"Ultimate":{"Character":"http://api.kuroganehammer.com/api/characters/name/PAC-MAN?game=ultimate"}},"Links":[{"Rel":"self","Href":"http://api.kuroganehammer.com/api/moves/ccce455573b0452394665585bc6b6816?game=smash4"},{"Rel":"character","Href":"http://api.kuroganehammer.com/api/characters/name/PAC-MAN?game=smash4"}]},{"InstanceId":"6846945b30904a97949e2a5fe6eaf338","Name":"Dash Attack (Hit 3)","OwnerId":38,"Owner":"PAC-MAN","HitboxActive":"30","FirstActionableFrame":"-","BaseDamage":"5","Angle":"60","BaseKnockBackSetKnockback":"100","LandingLag":null,"AutoCancel":null,"KnockbackGrowth":"60","MoveType":"ground","IsWeightDependent":false,"Game":"Smash4","Related":{"Smash4":{"Character":"http://api.kuroganehammer.com/api/characters/name/PAC-MAN?game=smash4","Self":"http://api.kuroganehammer.com/api/moves/6846945b30904a97949e2a5fe6eaf338?game=smash4"},"Ultimate":{"Character":"http://api.kuroganehammer.com/api/characters/name/PAC-MAN?game=ultimate"}},"Links":[{"Rel":"self","Href":"http://api.kuroganehammer.com/api/moves/6846945b30904a97949e2a5fe6eaf338?game=smash4"},{"Rel":"character","Href":"http://api.kuroganehammer.com/api/characters/name/PAC-MAN?game=smash4"}]},{"InstanceId":"c06e9e6131fa4b25808c25e3ee483f24","Name":"Ftilt (All Angles)","OwnerId":38,"Owner":"PAC-MAN","HitboxActive":"5-7","FirstActionableFrame":"31","BaseDamage":"8","Angle":"361","BaseKnockBackSetKnockback":"20","LandingLag":null,"AutoCancel":null,"KnockbackGrowth":"100","MoveType":"ground","IsWeightDependent":false,"Game":"Smash4","Related":{"Smash4":{"Character":"http://api.kuroganehammer.com/api/characters/name/PAC-MAN?game=smash4","Self":"http://api.kuroganehammer.com/api/moves/c06e9e6131fa4b25808c25e3ee483f24?game=smash4"},"Ultimate":{"Character":"http://api.kuroganehammer.com/api/characters/name/PAC-MAN?game=ultimate"}},"Links":[{"Rel":"self","Href":"http://api.kuroganehammer.com/api/moves/c06e9e6131fa4b25808c25e3ee483f24?game=smash4"},{"Rel":"character","Href":"http://api.kuroganehammer.com/api/characters/name/PAC-MAN?game=smash4"}]},{"InstanceId":"393a0424aaa24a8fb75576653986116f","Name":"Utilt","OwnerId":38,"Owner":"PAC-MAN","HitboxActive":"7-10 (Head Intangible: 6-10)","FirstActionableFrame":"34","BaseDamage":"7","Angle":"96","BaseKnockBackSetKnockback":"50","LandingLag":null,"AutoCancel":null,"KnockbackGrowth":"100","MoveType":"ground","IsWeightDependent":false,"Game":"Smash4","Related":{"Smash4":{"Character":"http://api.kuroganehammer.com/api/characters/name/PAC-MAN?game=smash4","Self":"http://api.kuroganehammer.com/api/moves/393a0424aaa24a8fb75576653986116f?game=smash4"},"Ultimate":{"Character":"http://api.kuroganehammer.com/api/characters/name/PAC-MAN?game=ultimate"}},"Links":[{"Rel":"self","Href":"http://api.kuroganehammer.com/api/moves/393a0424aaa24a8fb75576653986116f?game=smash4"},{"Rel":"character","Href":"http://api.kuroganehammer.com/api/characters/name/PAC-MAN?game=smash4"}]},{"InstanceId":"2505d44e0e5f4dcda816f9e093cc3db9","Name":"Dtilt","OwnerId":38,"Owner":"PAC-MAN","HitboxActive":"7-9","FirstActionableFrame":"29","BaseDamage":"6","Angle":"45","BaseKnockBackSetKnockback":"50","LandingLag":null,"AutoCancel":null,"KnockbackGrowth":"80","MoveType":"ground","IsWeightDependent":false,"Game":"Smash4","Related":{"Smash4":{"Character":"http://api.kuroganehammer.com/api/characters/name/PAC-MAN?game=smash4","Self":"http://api.kuroganehammer.com/api/moves/2505d44e0e5f4dcda816f9e093cc3db9?game=smash4"},"Ultimate":{"Character":"http://api.kuroganehammer.com/api/characters/name/PAC-MAN?game=ultimate"}},"Links":[{"Rel":"self","Href":"http://api.kuroganehammer.com/api/moves/2505d44e0e5f4dcda816f9e093cc3db9?game=smash4"},{"Rel":"character","Href":"http://api.kuroganehammer.com/api/characters/name/PAC-MAN?game=smash4"}]},{"InstanceId":"95daed4784f04493ab7a16b7bfde5daf","Name":"Fsmash","OwnerId":38,"Owner":"PAC-MAN","HitboxActive":"18-20","FirstActionableFrame":"53","BaseDamage":"16/15","Angle":"361","BaseKnockBackSetKnockback":"25","LandingLag":null,"AutoCancel":null,"KnockbackGrowth":"99","MoveType":"ground","IsWeightDependent":false,"Game":"Smash4","Related":{"Smash4":{"Character":"http://api.kuroganehammer.com/api/characters/name/PAC-MAN?game=smash4","Self":"http://api.kuroganehammer.com/api/moves/95daed4784f04493ab7a16b7bfde5daf?game=smash4"},"Ultimate":{"Character":"http://api.kuroganehammer.com/api/characters/name/PAC-MAN?game=ultimate"}},"Links":[{"Rel":"self","Href":"http://api.kuroganehammer.com/api/moves/95daed4784f04493ab7a16b7bfde5daf?game=smash4"},{"Rel":"character","Href":"http://api.kuroganehammer.com/api/characters/name/PAC-MAN?game=smash4"}]},{"InstanceId":"f5613e460f5941b29fd11cfdb3a56c5c","Name":"Fsmash (Late)","OwnerId":38,"Owner":"PAC-MAN","HitboxActive":"21-28","FirstActionableFrame":"-","BaseDamage":"9","Angle":"361","BaseKnockBackSetKnockback":"25","LandingLag":null,"AutoCancel":null,"KnockbackGrowth":"102","MoveType":"ground","IsWeightDependent":false,"Game":"Smash4","Related":{"Smash4":{"Character":"http://api.kuroganehammer.com/api/characters/name/PAC-MAN?game=smash4","Self":"http://api.kuroganehammer.com/api/moves/f5613e460f5941b29fd11cfdb3a56c5c?game=smash4"},"Ultimate":{"Character":"http://api.kuroganehammer.com/api/characters/name/PAC-MAN?game=ultimate"}},"Links":[{"Rel":"self","Href":"http://api.kuroganehammer.com/api/moves/f5613e460f5941b29fd11cfdb3a56c5c?game=smash4"},{"Rel":"character","Href":"http://api.kuroganehammer.com/api/characters/name/PAC-MAN?game=smash4"}]},{"InstanceId":"1e21299cbad347129a3f38e11ed1c0b7","Name":"Usmash (Hit 1)","OwnerId":38,"Owner":"PAC-MAN","HitboxActive":"13","FirstActionableFrame":"50","BaseDamage":"3","Angle":"115","BaseKnockBackSetKnockback":"95","LandingLag":null,"AutoCancel":null,"KnockbackGrowth":"20","MoveType":"ground","IsWeightDependent":false,"Game":"Smash4","Related":{"Smash4":{"Character":"http://api.kuroganehammer.com/api/characters/name/PAC-MAN?game=smash4","Self":"http://api.kuroganehammer.com/api/moves/1e21299cbad347129a3f38e11ed1c0b7?game=smash4"},"Ultimate":{"Character":"http://api.kuroganehammer.com/api/characters/name/PAC-MAN?game=ultimate"}},"Links":[{"Rel":"self","Href":"http://api.kuroganehammer.com/api/moves/1e21299cbad347129a3f38e11ed1c0b7?game=smash4"},{"Rel":"character","Href":"http://api.kuroganehammer.com/api/characters/name/PAC-MAN?game=smash4"}]},{"InstanceId":"774e0b9d010144c38d6e7d002e4e63a1","Name":"Usmash (Hit 2)","OwnerId":38,"Owner":"PAC-MAN","HitboxActive":"16-18","FirstActionableFrame":"-","BaseDamage":"14","Angle":"83","BaseKnockBackSetKnockback":"32","LandingLag":null,"AutoCancel":null,"KnockbackGrowth":"97","MoveType":"ground","IsWeightDependent":false,"Game":"Smash4","Related":{"Smash4":{"Character":"http://api.kuroganehammer.com/api/characters/name/PAC-MAN?game=smash4","Self":"http://api.kuroganehammer.com/api/moves/774e0b9d010144c38d6e7d002e4e63a1?game=smash4"},"Ultimate":{"Character":"http://api.kuroganehammer.com/api/characters/name/PAC-MAN?game=ultimate"}},"Links":[{"Rel":"self","Href":"http://api.kuroganehammer.com/api/moves/774e0b9d010144c38d6e7d002e4e63a1?game=smash4"},{"Rel":"character","Href":"http://api.kuroganehammer.com/api/characters/name/PAC-MAN?game=smash4"}]},{"InstanceId":"c70f9af826b64d75a45d7700b7a388db","Name":"Usmash (Hit 2, Late)","OwnerId":38,"Owner":"PAC-MAN","HitboxActive":"19-26","FirstActionableFrame":"-","BaseDamage":"8","Angle":"83","BaseKnockBackSetKnockback":"32","LandingLag":null,"AutoCancel":null,"KnockbackGrowth":"92","MoveType":"ground","IsWeightDependent":false,"Game":"Smash4","Related":{"Smash4":{"Character":"http://api.kuroganehammer.com/api/characters/name/PAC-MAN?game=smash4","Self":"http://api.kuroganehammer.com/api/moves/c70f9af826b64d75a45d7700b7a388db?game=smash4"},"Ultimate":{"Character":"http://api.kuroganehammer.com/api/characters/name/PAC-MAN?game=ultimate"}},"Links":[{"Rel":"self","Href":"http://api.kuroganehammer.com/api/moves/c70f9af826b64d75a45d7700b7a388db?game=smash4"},{"Rel":"character","Href":"http://api.kuroganehammer.com/api/characters/name/PAC-MAN?game=smash4"}]},{"InstanceId":"e548af2e9a0a4bd8ab6eee6b2716bf34","Name":"Dsmash","OwnerId":38,"Owner":"PAC-MAN","HitboxActive":"18-20","FirstActionableFrame":"55","BaseDamage":"13","Angle":"29","BaseKnockBackSetKnockback":"30","LandingLag":null,"AutoCancel":null,"KnockbackGrowth":"86","MoveType":"ground","IsWeightDependent":false,"Game":"Smash4","Related":{"Smash4":{"Character":"http://api.kuroganehammer.com/api/characters/name/PAC-MAN?game=smash4","Self":"http://api.kuroganehammer.com/api/moves/e548af2e9a0a4bd8ab6eee6b2716bf34?game=smash4"},"Ultimate":{"Character":"http://api.kuroganehammer.com/api/characters/name/PAC-MAN?game=ultimate"}},"Links":[{"Rel":"self","Href":"http://api.kuroganehammer.com/api/moves/e548af2e9a0a4bd8ab6eee6b2716bf34?game=smash4"},{"Rel":"character","Href":"http://api.kuroganehammer.com/api/characters/name/PAC-MAN?game=smash4"}]},{"InstanceId":"63bd66d53f4740a5bc841a53f35e1a36","Name":"Dsmash (Late)","OwnerId":38,"Owner":"PAC-MAN","HitboxActive":"21-28","FirstActionableFrame":"-","BaseDamage":"7","Angle":"45","BaseKnockBackSetKnockback":"40","LandingLag":null,"AutoCancel":null,"KnockbackGrowth":"92","MoveType":"ground","IsWeightDependent":false,"Game":"Smash4","Related":{"Smash4":{"Character":"http://api.kuroganehammer.com/api/characters/name/PAC-MAN?game=smash4","Self":"http://api.kuroganehammer.com/api/moves/63bd66d53f4740a5bc841a53f35e1a36?game=smash4"},"Ultimate":{"Character":"http://api.kuroganehammer.com/api/characters/name/PAC-MAN?game=ultimate"}},"Links":[{"Rel":"self","Href":"http://api.kuroganehammer.com/api/moves/63bd66d53f4740a5bc841a53f35e1a36?game=smash4"},{"Rel":"character","Href":"http://api.kuroganehammer.com/api/characters/name/PAC-MAN?game=smash4"}]},{"InstanceId":"f4ec2b371b044cf4bbe08f6d26da3ea4","Name":"Standing Grab","OwnerId":38,"Owner":"PAC-MAN","HitboxActive":"12-14, 22-24, 32-39","FirstActionableFrame":"76","BaseDamage":"","Angle":"","BaseKnockBackSetKnockback":"","LandingLag":null,"AutoCancel":null,"KnockbackGrowth":"","MoveType":"ground","IsWeightDependent":false,"Game":"Smash4","Related":{"Smash4":{"Character":"http://api.kuroganehammer.com/api/characters/name/PAC-MAN?game=smash4","Self":"http://api.kuroganehammer.com/api/moves/f4ec2b371b044cf4bbe08f6d26da3ea4?game=smash4"},"Ultimate":{"Character":"http://api.kuroganehammer.com/api/characters/name/PAC-MAN?game=ultimate"}},"Links":[{"Rel":"self","Href":"http://api.kuroganehammer.com/api/moves/f4ec2b371b044cf4bbe08f6d26da3ea4?game=smash4"},{"Rel":"character","Href":"http://api.kuroganehammer.com/api/characters/name/PAC-MAN?game=smash4"}]},{"InstanceId":"f21792f05b0840f393fe28d60cb6c376","Name":"Dash Grab","OwnerId":38,"Owner":"PAC-MAN","HitboxActive":"12-14, 22-24, 32-39","FirstActionableFrame":"76","BaseDamage":"","Angle":"","BaseKnockBackSetKnockback":"","LandingLag":null,"AutoCancel":null,"KnockbackGrowth":"","MoveType":"ground","IsWeightDependent":false,"Game":"Smash4","Related":{"Smash4":{"Character":"http://api.kuroganehammer.com/api/characters/name/PAC-MAN?game=smash4","Self":"http://api.kuroganehammer.com/api/moves/f21792f05b0840f393fe28d60cb6c376?game=smash4"},"Ultimate":{"Character":"http://api.kuroganehammer.com/api/characters/name/PAC-MAN?game=ultimate"}},"Links":[{"Rel":"self","Href":"http://api.kuroganehammer.com/api/moves/f21792f05b0840f393fe28d60cb6c376?game=smash4"},{"Rel":"character","Href":"http://api.kuroganehammer.com/api/characters/name/PAC-MAN?game=smash4"}]},{"InstanceId":"17e07cb1c1e2419c84a4a2a214163aad","Name":"Pivot Grab","OwnerId":38,"Owner":"PAC-MAN","HitboxActive":"12-14, 22-24, 32-39","FirstActionableFrame":"76","BaseDamage":"","Angle":"","BaseKnockBackSetKnockback":"","LandingLag":null,"AutoCancel":null,"KnockbackGrowth":"","MoveType":"ground","IsWeightDependent":false,"Game":"Smash4","Related":{"Smash4":{"Character":"http://api.kuroganehammer.com/api/characters/name/PAC-MAN?game=smash4","Self":"http://api.kuroganehammer.com/api/moves/17e07cb1c1e2419c84a4a2a214163aad?game=smash4"},"Ultimate":{"Character":"http://api.kuroganehammer.com/api/characters/name/PAC-MAN?game=ultimate"}},"Links":[{"Rel":"self","Href":"http://api.kuroganehammer.com/api/moves/17e07cb1c1e2419c84a4a2a214163aad?game=smash4"},{"Rel":"character","Href":"http://api.kuroganehammer.com/api/characters/name/PAC-MAN?game=smash4"}]},{"InstanceId":"0dd2076986fa4b6abe99c0b0fe6fd1ab","Name":"Spotdodge","OwnerId":38,"Owner":"PAC-MAN","HitboxActive":"3-17","FirstActionableFrame":"27","BaseDamage":"","Angle":"","BaseKnockBackSetKnockback":"","LandingLag":null,"AutoCancel":null,"KnockbackGrowth":"","MoveType":"ground","IsWeightDependent":false,"Game":"Smash4","Related":{"Smash4":{"Character":"http://api.kuroganehammer.com/api/characters/name/PAC-MAN?game=smash4","Self":"http://api.kuroganehammer.com/api/moves/0dd2076986fa4b6abe99c0b0fe6fd1ab?game=smash4"},"Ultimate":{"Character":"http://api.kuroganehammer.com/api/characters/name/PAC-MAN?game=ultimate"}},"Links":[{"Rel":"self","Href":"http://api.kuroganehammer.com/api/moves/0dd2076986fa4b6abe99c0b0fe6fd1ab?game=smash4"},{"Rel":"character","Href":"http://api.kuroganehammer.com/api/characters/name/PAC-MAN?game=smash4"}]},{"InstanceId":"8efaf5993e9740499c1577ff61deafd4","Name":"Forward Roll","OwnerId":38,"Owner":"PAC-MAN","HitboxActive":"4-16","FirstActionableFrame":"30","BaseDamage":"","Angle":"","BaseKnockBackSetKnockback":"","LandingLag":null,"AutoCancel":null,"KnockbackGrowth":"","MoveType":"ground","IsWeightDependent":false,"Game":"Smash4","Related":{"Smash4":{"Character":"http://api.kuroganehammer.com/api/characters/name/PAC-MAN?game=smash4","Self":"http://api.kuroganehammer.com/api/moves/8efaf5993e9740499c1577ff61deafd4?game=smash4"},"Ultimate":{"Character":"http://api.kuroganehammer.com/api/characters/name/PAC-MAN?game=ultimate"}},"Links":[{"Rel":"self","Href":"http://api.kuroganehammer.com/api/moves/8efaf5993e9740499c1577ff61deafd4?game=smash4"},{"Rel":"character","Href":"http://api.kuroganehammer.com/api/characters/name/PAC-MAN?game=smash4"}]},{"InstanceId":"b816749f425f4af385e533fbfb132a13","Name":"Back Roll","OwnerId":38,"Owner":"PAC-MAN","HitboxActive":"4-16","FirstActionableFrame":"30","BaseDamage":"","Angle":"","BaseKnockBackSetKnockback":"","LandingLag":null,"AutoCancel":null,"KnockbackGrowth":"","MoveType":"ground","IsWeightDependent":false,"Game":"Smash4","Related":{"Smash4":{"Character":"http://api.kuroganehammer.com/api/characters/name/PAC-MAN?game=smash4","Self":"http://api.kuroganehammer.com/api/moves/b816749f425f4af385e533fbfb132a13?game=smash4"},"Ultimate":{"Character":"http://api.kuroganehammer.com/api/characters/name/PAC-MAN?game=ultimate"}},"Links":[{"Rel":"self","Href":"http://api.kuroganehammer.com/api/moves/b816749f425f4af385e533fbfb132a13?game=smash4"},{"Rel":"character","Href":"http://api.kuroganehammer.com/api/characters/name/PAC-MAN?game=smash4"}]},{"InstanceId":"0470c7cb8de545488b42c96b87eca5cc","Name":"Airdodge","OwnerId":38,"Owner":"PAC-MAN","HitboxActive":"3-27","FirstActionableFrame":"33","BaseDamage":"","Angle":"","BaseKnockBackSetKnockback":"","LandingLag":null,"AutoCancel":null,"KnockbackGrowth":"","MoveType":"ground","IsWeightDependent":false,"Game":"Smash4","Related":{"Smash4":{"Character":"http://api.kuroganehammer.com/api/characters/name/PAC-MAN?game=smash4","Self":"http://api.kuroganehammer.com/api/moves/0470c7cb8de545488b42c96b87eca5cc?game=smash4"},"Ultimate":{"Character":"http://api.kuroganehammer.com/api/characters/name/PAC-MAN?game=ultimate"}},"Links":[{"Rel":"self","Href":"http://api.kuroganehammer.com/api/moves/0470c7cb8de545488b42c96b87eca5cc?game=smash4"},{"Rel":"character","Href":"http://api.kuroganehammer.com/api/characters/name/PAC-MAN?game=smash4"}]},{"InstanceId":"c32494ab9d3645f09463e810981fc1d4","Name":"Nair (Early)","OwnerId":38,"Owner":"PAC-MAN","HitboxActive":"3-5","FirstActionableFrame":"52","BaseDamage":"10","Angle":"361","BaseKnockBackSetKnockback":"20","LandingLag":"12","AutoCancel":"1-2, 48>","KnockbackGrowth":"100","MoveType":"aerial","IsWeightDependent":false,"Game":"Smash4","Related":{"Smash4":{"Character":"http://api.kuroganehammer.com/api/characters/name/PAC-MAN?game=smash4","Self":"http://api.kuroganehammer.com/api/moves/c32494ab9d3645f09463e810981fc1d4?game=smash4"},"Ultimate":{"Character":"http://api.kuroganehammer.com/api/characters/name/PAC-MAN?game=ultimate"}},"Links":[{"Rel":"self","Href":"http://api.kuroganehammer.com/api/moves/c32494ab9d3645f09463e810981fc1d4?game=smash4"},{"Rel":"character","Href":"http://api.kuroganehammer.com/api/characters/name/PAC-MAN?game=smash4"}]},{"InstanceId":"bd4fd8170b724897af4ad7f8ee80405d","Name":"Nair","OwnerId":38,"Owner":"PAC-MAN","HitboxActive":"6-9","FirstActionableFrame":"-","BaseDamage":"6","Angle":"361","BaseKnockBackSetKnockback":"13","LandingLag":"-","AutoCancel":"-","KnockbackGrowth":"90","MoveType":"aerial","IsWeightDependent":false,"Game":"Smash4","Related":{"Smash4":{"Character":"http://api.kuroganehammer.com/api/characters/name/PAC-MAN?game=smash4","Self":"http://api.kuroganehammer.com/api/moves/bd4fd8170b724897af4ad7f8ee80405d?game=smash4"},"Ultimate":{"Character":"http://api.kuroganehammer.com/api/characters/name/PAC-MAN?game=ultimate"}},"Links":[{"Rel":"self","Href":"http://api.kuroganehammer.com/api/moves/bd4fd8170b724897af4ad7f8ee80405d?game=smash4"},{"Rel":"character","Href":"http://api.kuroganehammer.com/api/characters/name/PAC-MAN?game=smash4"}]},{"InstanceId":"8da850d6467d4f1f97755700d0ffd1fe","Name":"Nair (Late)","OwnerId":38,"Owner":"PAC-MAN","HitboxActive":"10-19","FirstActionableFrame":"-","BaseDamage":"3","Angle":"361","BaseKnockBackSetKnockback":"13","LandingLag":"-","AutoCancel":"-","KnockbackGrowth":"90","MoveType":"aerial","IsWeightDependent":false,"Game":"Smash4","Related":{"Smash4":{"Character":"http://api.kuroganehammer.com/api/characters/name/PAC-MAN?game=smash4","Self":"http://api.kuroganehammer.com/api/moves/8da850d6467d4f1f97755700d0ffd1fe?game=smash4"},"Ultimate":{"Character":"http://api.kuroganehammer.com/api/characters/name/PAC-MAN?game=ultimate"}},"Links":[{"Rel":"self","Href":"http://api.kuroganehammer.com/api/moves/8da850d6467d4f1f97755700d0ffd1fe?game=smash4"},{"Rel":"character","Href":"http://api.kuroganehammer.com/api/characters/name/PAC-MAN?game=smash4"}]},{"InstanceId":"19988bd0016444d4b8a063b684f08610","Name":"Fair","OwnerId":38,"Owner":"PAC-MAN","HitboxActive":"5-8","FirstActionableFrame":"26","BaseDamage":"5.3","Angle":"361","BaseKnockBackSetKnockback":"7","LandingLag":"16","AutoCancel":"1, 43>","KnockbackGrowth":"90","MoveType":"aerial","IsWeightDependent":false,"Game":"Smash4","Related":{"Smash4":{"Character":"http://api.kuroganehammer.com/api/characters/name/PAC-MAN?game=smash4","Self":"http://api.kuroganehammer.com/api/moves/19988bd0016444d4b8a063b684f08610?game=smash4"},"Ultimate":{"Character":"http://api.kuroganehammer.com/api/characters/name/PAC-MAN?game=ultimate"}},"Links":[{"Rel":"self","Href":"http://api.kuroganehammer.com/api/moves/19988bd0016444d4b8a063b684f08610?game=smash4"},{"Rel":"character","Href":"http://api.kuroganehammer.com/api/characters/name/PAC-MAN?game=smash4"}]},{"InstanceId":"4da102118bc2405dba1693904f6ecfe3","Name":"Bair","OwnerId":38,"Owner":"PAC-MAN","HitboxActive":"9-11","FirstActionableFrame":"41","BaseDamage":"11.8","Angle":"361","BaseKnockBackSetKnockback":"10","LandingLag":"22","AutoCancel":"1-8, 36>","KnockbackGrowth":"100","MoveType":"aerial","IsWeightDependent":false,"Game":"Smash4","Related":{"Smash4":{"Character":"http://api.kuroganehammer.com/api/characters/name/PAC-MAN?game=smash4","Self":"http://api.kuroganehammer.com/api/moves/4da102118bc2405dba1693904f6ecfe3?game=smash4"},"Ultimate":{"Character":"http://api.kuroganehammer.com/api/characters/name/PAC-MAN?game=ultimate"}},"Links":[{"Rel":"self","Href":"http://api.kuroganehammer.com/api/moves/4da102118bc2405dba1693904f6ecfe3?game=smash4"},{"Rel":"character","Href":"http://api.kuroganehammer.com/api/characters/name/PAC-MAN?game=smash4"}]},{"InstanceId":"940db3b427a64a79b70daa5b651d0b34","Name":"Bair (Late)","OwnerId":38,"Owner":"PAC-MAN","HitboxActive":"12-16","FirstActionableFrame":"-","BaseDamage":"7","Angle":"361","BaseKnockBackSetKnockback":"7","LandingLag":"-","AutoCancel":"-","KnockbackGrowth":"90","MoveType":"aerial","IsWeightDependent":false,"Game":"Smash4","Related":{"Smash4":{"Character":"http://api.kuroganehammer.com/api/characters/name/PAC-MAN?game=smash4","Self":"http://api.kuroganehammer.com/api/moves/940db3b427a64a79b70daa5b651d0b34?game=smash4"},"Ultimate":{"Character":"http://api.kuroganehammer.com/api/characters/name/PAC-MAN?game=ultimate"}},"Links":[{"Rel":"self","Href":"http://api.kuroganehammer.com/api/moves/940db3b427a64a79b70daa5b651d0b34?game=smash4"},{"Rel":"character","Href":"http://api.kuroganehammer.com/api/characters/name/PAC-MAN?game=smash4"}]},{"InstanceId":"7bdd21e4343b4422908abc82b58ef4e2","Name":"Uair","OwnerId":38,"Owner":"PAC-MAN","HitboxActive":"9-16","FirstActionableFrame":"37","BaseDamage":"10","Angle":"70","BaseKnockBackSetKnockback":"13","LandingLag":"16","AutoCancel":"1, 32>","KnockbackGrowth":"100","MoveType":"aerial","IsWeightDependent":false,"Game":"Smash4","Related":{"Smash4":{"Character":"http://api.kuroganehammer.com/api/characters/name/PAC-MAN?game=smash4","Self":"http://api.kuroganehammer.com/api/moves/7bdd21e4343b4422908abc82b58ef4e2?game=smash4"},"Ultimate":{"Character":"http://api.kuroganehammer.com/api/characters/name/PAC-MAN?game=ultimate"}},"Links":[{"Rel":"self","Href":"http://api.kuroganehammer.com/api/moves/7bdd21e4343b4422908abc82b58ef4e2?game=smash4"},{"Rel":"character","Href":"http://api.kuroganehammer.com/api/characters/name/PAC-MAN?game=smash4"}]},{"InstanceId":"82c0a64c4ef74ec99a145dc733ec137a","Name":"Dair (Hits 1-3)","OwnerId":38,"Owner":"PAC-MAN","HitboxActive":"6-7, 14-15, 22-23","FirstActionableFrame":"60","BaseDamage":"1.5","Angle":"100","BaseKnockBackSetKnockback":"W: 10","LandingLag":"20","AutoCancel":"1, 56>","KnockbackGrowth":"100","MoveType":"aerial","IsWeightDependent":false,"Game":"Smash4","Related":{"Smash4":{"Character":"http://api.kuroganehammer.com/api/characters/name/PAC-MAN?game=smash4","Self":"http://api.kuroganehammer.com/api/moves/82c0a64c4ef74ec99a145dc733ec137a?game=smash4"},"Ultimate":{"Character":"http://api.kuroganehammer.com/api/characters/name/PAC-MAN?game=ultimate"}},"Links":[{"Rel":"self","Href":"http://api.kuroganehammer.com/api/moves/82c0a64c4ef74ec99a145dc733ec137a?game=smash4"},{"Rel":"character","Href":"http://api.kuroganehammer.com/api/characters/name/PAC-MAN?game=smash4"}]},{"InstanceId":"acf8a8434210433c822b014355282970","Name":"Dair (Hit 4)","OwnerId":38,"Owner":"PAC-MAN","HitboxActive":"30-31","FirstActionableFrame":"-","BaseDamage":"6","Angle":"65","BaseKnockBackSetKnockback":"80","LandingLag":"-","AutoCancel":"-","KnockbackGrowth":"90","MoveType":"aerial","IsWeightDependent":false,"Game":"Smash4","Related":{"Smash4":{"Character":"http://api.kuroganehammer.com/api/characters/name/PAC-MAN?game=smash4","Self":"http://api.kuroganehammer.com/api/moves/acf8a8434210433c822b014355282970?game=smash4"},"Ultimate":{"Character":"http://api.kuroganehammer.com/api/characters/name/PAC-MAN?game=ultimate"}},"Links":[{"Rel":"self","Href":"http://api.kuroganehammer.com/api/moves/acf8a8434210433c822b014355282970?game=smash4"},{"Rel":"character","Href":"http://api.kuroganehammer.com/api/characters/name/PAC-MAN?game=smash4"}]},{"InstanceId":"ae8e729e36164efe8a6875e33c071c3b","Name":"Bonus Fruit (Throw)","OwnerId":38,"Owner":"PAC-MAN","HitboxActive":"12-","FirstActionableFrame":"45","BaseDamage":"-","Angle":"-","BaseKnockBackSetKnockback":"-","LandingLag":null,"AutoCancel":null,"KnockbackGrowth":"-","MoveType":"special","IsWeightDependent":false,"Game":"Smash4","Related":{"Smash4":{"Character":"http://api.kuroganehammer.com/api/characters/name/PAC-MAN?game=smash4","Self":"http://api.kuroganehammer.com/api/moves/ae8e729e36164efe8a6875e33c071c3b?game=smash4"},"Ultimate":{"Character":"http://api.kuroganehammer.com/api/characters/name/PAC-MAN?game=ultimate"}},"Links":[{"Rel":"self","Href":"http://api.kuroganehammer.com/api/moves/ae8e729e36164efe8a6875e33c071c3b?game=smash4"},{"Rel":"character","Href":"http://api.kuroganehammer.com/api/characters/name/PAC-MAN?game=smash4"}]},{"InstanceId":"920d63025a0448db9a483f9a9a42322e","Name":"Bonus Fruit (CHERRY)","OwnerId":38,"Owner":"PAC-MAN","HitboxActive":"Fruit Generated: Frame 8","FirstActionableFrame":"-","BaseDamage":"4","Angle":"55","BaseKnockBackSetKnockback":"40","LandingLag":null,"AutoCancel":null,"KnockbackGrowth":"80","MoveType":"special","IsWeightDependent":false,"Game":"Smash4","Related":{"Smash4":{"Character":"http://api.kuroganehammer.com/api/characters/name/PAC-MAN?game=smash4","Self":"http://api.kuroganehammer.com/api/moves/920d63025a0448db9a483f9a9a42322e?game=smash4"},"Ultimate":{"Character":"http://api.kuroganehammer.com/api/characters/name/PAC-MAN?game=ultimate"}},"Links":[{"Rel":"self","Href":"http://api.kuroganehammer.com/api/moves/920d63025a0448db9a483f9a9a42322e?game=smash4"},{"Rel":"character","Href":"http://api.kuroganehammer.com/api/characters/name/PAC-MAN?game=smash4"}]},{"InstanceId":"24e9f10ab2354286ac71db28aabef4e4","Name":"Bonus Fruit (STRAWBERRY)","OwnerId":38,"Owner":"PAC-MAN","HitboxActive":"Fruit Generated: Frame 19","FirstActionableFrame":"-","BaseDamage":"6","Angle":"55","BaseKnockBackSetKnockback":"40","LandingLag":null,"AutoCancel":null,"KnockbackGrowth":"80","MoveType":"special","IsWeightDependent":false,"Game":"Smash4","Related":{"Smash4":{"Character":"http://api.kuroganehammer.com/api/characters/name/PAC-MAN?game=smash4","Self":"http://api.kuroganehammer.com/api/moves/24e9f10ab2354286ac71db28aabef4e4?game=smash4"},"Ultimate":{"Character":"http://api.kuroganehammer.com/api/characters/name/PAC-MAN?game=ultimate"}},"Links":[{"Rel":"self","Href":"http://api.kuroganehammer.com/api/moves/24e9f10ab2354286ac71db28aabef4e4?game=smash4"},{"Rel":"character","Href":"http://api.kuroganehammer.com/api/characters/name/PAC-MAN?game=smash4"}]},{"InstanceId":"fa3cdc4e4adc41609fb8712939379d7b","Name":"Bonus Fruit (ORANGE)","OwnerId":38,"Owner":"PAC-MAN","HitboxActive":"Fruit Generated: Frame 30","FirstActionableFrame":"-","BaseDamage":"8","Angle":"30","BaseKnockBackSetKnockback":"50","LandingLag":null,"AutoCancel":null,"KnockbackGrowth":"76","MoveType":"special","IsWeightDependent":false,"Game":"Smash4","Related":{"Smash4":{"Character":"http://api.kuroganehammer.com/api/characters/name/PAC-MAN?game=smash4","Self":"http://api.kuroganehammer.com/api/moves/fa3cdc4e4adc41609fb8712939379d7b?game=smash4"},"Ultimate":{"Character":"http://api.kuroganehammer.com/api/characters/name/PAC-MAN?game=ultimate"}},"Links":[{"Rel":"self","Href":"http://api.kuroganehammer.com/api/moves/fa3cdc4e4adc41609fb8712939379d7b?game=smash4"},{"Rel":"character","Href":"http://api.kuroganehammer.com/api/characters/name/PAC-MAN?game=smash4"}]},{"InstanceId":"5c7cd6d5e3b0421b949d54c12ee6e058","Name":"Bonus Fruit (APPLE)","OwnerId":38,"Owner":"PAC-MAN","HitboxActive":"Fruit Generated: Frame 54","FirstActionableFrame":"-","BaseDamage":"9","Angle":"75","BaseKnockBackSetKnockback":"60","LandingLag":null,"AutoCancel":null,"KnockbackGrowth":"100","MoveType":"special","IsWeightDependent":false,"Game":"Smash4","Related":{"Smash4":{"Character":"http://api.kuroganehammer.com/api/characters/name/PAC-MAN?game=smash4","Self":"http://api.kuroganehammer.com/api/moves/5c7cd6d5e3b0421b949d54c12ee6e058?game=smash4"},"Ultimate":{"Character":"http://api.kuroganehammer.com/api/characters/name/PAC-MAN?game=ultimate"}},"Links":[{"Rel":"self","Href":"http://api.kuroganehammer.com/api/moves/5c7cd6d5e3b0421b949d54c12ee6e058?game=smash4"},{"Rel":"character","Href":"http://api.kuroganehammer.com/api/characters/name/PAC-MAN?game=smash4"}]},{"InstanceId":"95d2915cac1a408ba52b4a2b008a4bd4","Name":"Bonus Fruit (MELON)","OwnerId":38,"Owner":"PAC-MAN","HitboxActive":"Fruit Generated: Frame 78","FirstActionableFrame":"-","BaseDamage":"12","Angle":"55","BaseKnockBackSetKnockback":"40","LandingLag":null,"AutoCancel":null,"KnockbackGrowth":"100","MoveType":"special","IsWeightDependent":false,"Game":"Smash4","Related":{"Smash4":{"Character":"http://api.kuroganehammer.com/api/characters/name/PAC-MAN?game=smash4","Self":"http://api.kuroganehammer.com/api/moves/95d2915cac1a408ba52b4a2b008a4bd4?game=smash4"},"Ultimate":{"Character":"http://api.kuroganehammer.com/api/characters/name/PAC-MAN?game=ultimate"}},"Links":[{"Rel":"self","Href":"http://api.kuroganehammer.com/api/moves/95d2915cac1a408ba52b4a2b008a4bd4?game=smash4"},{"Rel":"character","Href":"http://api.kuroganehammer.com/api/characters/name/PAC-MAN?game=smash4"}]},{"InstanceId":"5d86b813b2074867b04d525d78cf718b","Name":"Bonus Fruit (GALAGA)","OwnerId":38,"Owner":"PAC-MAN","HitboxActive":"Fruit Generated: Frame 102","FirstActionableFrame":"-","BaseDamage":"9","Angle":"70","BaseKnockBackSetKnockback":"40","LandingLag":null,"AutoCancel":null,"KnockbackGrowth":"80","MoveType":"special","IsWeightDependent":false,"Game":"Smash4","Related":{"Smash4":{"Character":"http://api.kuroganehammer.com/api/characters/name/PAC-MAN?game=smash4","Self":"http://api.kuroganehammer.com/api/moves/5d86b813b2074867b04d525d78cf718b?game=smash4"},"Ultimate":{"Character":"http://api.kuroganehammer.com/api/characters/name/PAC-MAN?game=ultimate"}},"Links":[{"Rel":"self","Href":"http://api.kuroganehammer.com/api/moves/5d86b813b2074867b04d525d78cf718b?game=smash4"},{"Rel":"character","Href":"http://api.kuroganehammer.com/api/characters/name/PAC-MAN?game=smash4"}]},{"InstanceId":"0fc914adbca84396b6c8d76e97c1fc86","Name":"Bonus Fruit (BELL)","OwnerId":38,"Owner":"PAC-MAN","HitboxActive":"Fruit Generated: Frame 126","FirstActionableFrame":"-","BaseDamage":"8","Angle":"55","BaseKnockBackSetKnockback":"30","LandingLag":null,"AutoCancel":null,"KnockbackGrowth":"120","MoveType":"special","IsWeightDependent":false,"Game":"Smash4","Related":{"Smash4":{"Character":"http://api.kuroganehammer.com/api/characters/name/PAC-MAN?game=smash4","Self":"http://api.kuroganehammer.com/api/moves/0fc914adbca84396b6c8d76e97c1fc86?game=smash4"},"Ultimate":{"Character":"http://api.kuroganehammer.com/api/characters/name/PAC-MAN?game=ultimate"}},"Links":[{"Rel":"self","Href":"http://api.kuroganehammer.com/api/moves/0fc914adbca84396b6c8d76e97c1fc86?game=smash4"},{"Rel":"character","Href":"http://api.kuroganehammer.com/api/characters/name/PAC-MAN?game=smash4"}]},{"InstanceId":"b689cb860a734cb79f8726902fa47724","Name":"Bonus Fruit (KEY)","OwnerId":38,"Owner":"PAC-MAN","HitboxActive":"Fruit Generated: Frame 150","FirstActionableFrame":"-","BaseDamage":"15","Angle":"55","BaseKnockBackSetKnockback":"40","LandingLag":null,"AutoCancel":null,"KnockbackGrowth":"90","MoveType":"special","IsWeightDependent":false,"Game":"Smash4","Related":{"Smash4":{"Character":"http://api.kuroganehammer.com/api/characters/name/PAC-MAN?game=smash4","Self":"http://api.kuroganehammer.com/api/moves/b689cb860a734cb79f8726902fa47724?game=smash4"},"Ultimate":{"Character":"http://api.kuroganehammer.com/api/characters/name/PAC-MAN?game=ultimate"}},"Links":[{"Rel":"self","Href":"http://api.kuroganehammer.com/api/moves/b689cb860a734cb79f8726902fa47724?game=smash4"},{"Rel":"character","Href":"http://api.kuroganehammer.com/api/characters/name/PAC-MAN?game=smash4"}]},{"InstanceId":"d55bc09a120644ad98ce1ee18e540d2d","Name":"Power Pellet","OwnerId":38,"Owner":"PAC-MAN","HitboxActive":"23-","FirstActionableFrame":"94","BaseDamage":"10","Angle":"45","BaseKnockBackSetKnockback":"30","LandingLag":null,"AutoCancel":null,"KnockbackGrowth":"90","MoveType":"special","IsWeightDependent":false,"Game":"Smash4","Related":{"Smash4":{"Character":"http://api.kuroganehammer.com/api/characters/name/PAC-MAN?game=smash4","Self":"http://api.kuroganehammer.com/api/moves/d55bc09a120644ad98ce1ee18e540d2d?game=smash4"},"Ultimate":{"Character":"http://api.kuroganehammer.com/api/characters/name/PAC-MAN?game=ultimate"}},"Links":[{"Rel":"self","Href":"http://api.kuroganehammer.com/api/moves/d55bc09a120644ad98ce1ee18e540d2d?game=smash4"},{"Rel":"character","Href":"http://api.kuroganehammer.com/api/characters/name/PAC-MAN?game=smash4"}]},{"InstanceId":"e311c609391740a7bcb01603cc0bd74d","Name":"Power Pellet (Dash)","OwnerId":38,"Owner":"PAC-MAN","HitboxActive":"?? (Super Armor: ??)","FirstActionableFrame":"-","BaseDamage":"1","Angle":"50/361","BaseKnockBackSetKnockback":"50/40","LandingLag":null,"AutoCancel":null,"KnockbackGrowth":"108/66","MoveType":"special","IsWeightDependent":false,"Game":"Smash4","Related":{"Smash4":{"Character":"http://api.kuroganehammer.com/api/characters/name/PAC-MAN?game=smash4","Self":"http://api.kuroganehammer.com/api/moves/e311c609391740a7bcb01603cc0bd74d?game=smash4"},"Ultimate":{"Character":"http://api.kuroganehammer.com/api/characters/name/PAC-MAN?game=ultimate"}},"Links":[{"Rel":"self","Href":"http://api.kuroganehammer.com/api/moves/e311c609391740a7bcb01603cc0bd74d?game=smash4"},{"Rel":"character","Href":"http://api.kuroganehammer.com/api/characters/name/PAC-MAN?game=smash4"}]},{"InstanceId":"4de473b65eef4f519b13f3412d200dea","Name":"Pac-Jump","OwnerId":38,"Owner":"PAC-MAN","HitboxActive":"Trampoline From: 1-295 (Unblockable)","FirstActionableFrame":"-","BaseDamage":"-","Angle":"-","BaseKnockBackSetKnockback":"-","LandingLag":null,"AutoCancel":null,"KnockbackGrowth":"-","MoveType":"special","IsWeightDependent":false,"Game":"Smash4","Related":{"Smash4":{"Character":"http://api.kuroganehammer.com/api/characters/name/PAC-MAN?game=smash4","Self":"http://api.kuroganehammer.com/api/moves/4de473b65eef4f519b13f3412d200dea?game=smash4"},"Ultimate":{"Character":"http://api.kuroganehammer.com/api/characters/name/PAC-MAN?game=ultimate"}},"Links":[{"Rel":"self","Href":"http://api.kuroganehammer.com/api/moves/4de473b65eef4f519b13f3412d200dea?game=smash4"},{"Rel":"character","Href":"http://api.kuroganehammer.com/api/characters/name/PAC-MAN?game=smash4"}]},{"InstanceId":"44f10446506545d9b134cc5240f94db2","Name":"Pac-Jump (Attack, Early)","OwnerId":38,"Owner":"PAC-MAN","HitboxActive":"4-7","FirstActionableFrame":"-","BaseDamage":"7","Angle":"92","BaseKnockBackSetKnockback":"40","LandingLag":null,"AutoCancel":null,"KnockbackGrowth":"90","MoveType":"special","IsWeightDependent":false,"Game":"Smash4","Related":{"Smash4":{"Character":"http://api.kuroganehammer.com/api/characters/name/PAC-MAN?game=smash4","Self":"http://api.kuroganehammer.com/api/moves/44f10446506545d9b134cc5240f94db2?game=smash4"},"Ultimate":{"Character":"http://api.kuroganehammer.com/api/characters/name/PAC-MAN?game=ultimate"}},"Links":[{"Rel":"self","Href":"http://api.kuroganehammer.com/api/moves/44f10446506545d9b134cc5240f94db2?game=smash4"},{"Rel":"character","Href":"http://api.kuroganehammer.com/api/characters/name/PAC-MAN?game=smash4"}]},{"InstanceId":"71e59a56ecae4b18b40bef5b9538faaa","Name":"Pac-Jump (Attack)","OwnerId":38,"Owner":"PAC-MAN","HitboxActive":"8-12","FirstActionableFrame":"-","BaseDamage":"6","Angle":"86","BaseKnockBackSetKnockback":"40","LandingLag":null,"AutoCancel":null,"KnockbackGrowth":"90","MoveType":"special","IsWeightDependent":false,"Game":"Smash4","Related":{"Smash4":{"Character":"http://api.kuroganehammer.com/api/characters/name/PAC-MAN?game=smash4","Self":"http://api.kuroganehammer.com/api/moves/71e59a56ecae4b18b40bef5b9538faaa?game=smash4"},"Ultimate":{"Character":"http://api.kuroganehammer.com/api/characters/name/PAC-MAN?game=ultimate"}},"Links":[{"Rel":"self","Href":"http://api.kuroganehammer.com/api/moves/71e59a56ecae4b18b40bef5b9538faaa?game=smash4"},{"Rel":"character","Href":"http://api.kuroganehammer.com/api/characters/name/PAC-MAN?game=smash4"}]},{"InstanceId":"56effc27f67b44cb914f097a97d16c36","Name":"Pac-Jump (Attack, Late)","OwnerId":38,"Owner":"PAC-MAN","HitboxActive":"13-17","FirstActionableFrame":"-","BaseDamage":"5","Angle":"50","BaseKnockBackSetKnockback":"40","LandingLag":null,"AutoCancel":null,"KnockbackGrowth":"90","MoveType":"special","IsWeightDependent":false,"Game":"Smash4","Related":{"Smash4":{"Character":"http://api.kuroganehammer.com/api/characters/name/PAC-MAN?game=smash4","Self":"http://api.kuroganehammer.com/api/moves/56effc27f67b44cb914f097a97d16c36?game=smash4"},"Ultimate":{"Character":"http://api.kuroganehammer.com/api/characters/name/PAC-MAN?game=ultimate"}},"Links":[{"Rel":"self","Href":"http://api.kuroganehammer.com/api/moves/56effc27f67b44cb914f097a97d16c36?game=smash4"},{"Rel":"character","Href":"http://api.kuroganehammer.com/api/characters/name/PAC-MAN?game=smash4"}]},{"InstanceId":"b7e50477bfa842d4bf0ca40d6885fa99","Name":"Fire Hydrant","OwnerId":38,"Owner":"PAC-MAN","HitboxActive":"Hydrant Appears: 12","FirstActionableFrame":"40","BaseDamage":"-","Angle":"-","BaseKnockBackSetKnockback":"-","LandingLag":null,"AutoCancel":null,"KnockbackGrowth":"-","MoveType":"special","IsWeightDependent":false,"Game":"Smash4","Related":{"Smash4":{"Character":"http://api.kuroganehammer.com/api/characters/name/PAC-MAN?game=smash4","Self":"http://api.kuroganehammer.com/api/moves/b7e50477bfa842d4bf0ca40d6885fa99?game=smash4"},"Ultimate":{"Character":"http://api.kuroganehammer.com/api/characters/name/PAC-MAN?game=ultimate"}},"Links":[{"Rel":"self","Href":"http://api.kuroganehammer.com/api/moves/b7e50477bfa842d4bf0ca40d6885fa99?game=smash4"},{"Rel":"character","Href":"http://api.kuroganehammer.com/api/characters/name/PAC-MAN?game=smash4"}]},{"InstanceId":"9e054d07cb364cc2ad8a4de3a0007774","Name":"Fire Hydrant (Air)","OwnerId":38,"Owner":"PAC-MAN","HitboxActive":"Hydrant Appears: 9","FirstActionableFrame":"35","BaseDamage":"-","Angle":"-","BaseKnockBackSetKnockback":"-","LandingLag":null,"AutoCancel":null,"KnockbackGrowth":"-","MoveType":"special","IsWeightDependent":false,"Game":"Smash4","Related":{"Smash4":{"Character":"http://api.kuroganehammer.com/api/characters/name/PAC-MAN?game=smash4","Self":"http://api.kuroganehammer.com/api/moves/9e054d07cb364cc2ad8a4de3a0007774?game=smash4"},"Ultimate":{"Character":"http://api.kuroganehammer.com/api/characters/name/PAC-MAN?game=ultimate"}},"Links":[{"Rel":"self","Href":"http://api.kuroganehammer.com/api/moves/9e054d07cb364cc2ad8a4de3a0007774?game=smash4"},{"Rel":"character","Href":"http://api.kuroganehammer.com/api/characters/name/PAC-MAN?game=smash4"}]},{"InstanceId":"8e99141e6f2c4c87a42378fa4e84dcb3","Name":"Fire Hydrant (Drop Hitbox)","OwnerId":38,"Owner":"PAC-MAN","HitboxActive":"12-","FirstActionableFrame":"-","BaseDamage":"9","Angle":"60","BaseKnockBackSetKnockback":"60","LandingLag":null,"AutoCancel":null,"KnockbackGrowth":"80","MoveType":"special","IsWeightDependent":false,"Game":"Smash4","Related":{"Smash4":{"Character":"http://api.kuroganehammer.com/api/characters/name/PAC-MAN?game=smash4","Self":"http://api.kuroganehammer.com/api/moves/8e99141e6f2c4c87a42378fa4e84dcb3?game=smash4"},"Ultimate":{"Character":"http://api.kuroganehammer.com/api/characters/name/PAC-MAN?game=ultimate"}},"Links":[{"Rel":"self","Href":"http://api.kuroganehammer.com/api/moves/8e99141e6f2c4c87a42378fa4e84dcb3?game=smash4"},{"Rel":"character","Href":"http://api.kuroganehammer.com/api/characters/name/PAC-MAN?game=smash4"}]},{"InstanceId":"54fd4ceef3fe400abbec5a1e346649b1","Name":"Fire Hydrant (Damaged Hitbox)","OwnerId":38,"Owner":"PAC-MAN","HitboxActive":"1-","FirstActionableFrame":"-","BaseDamage":"13","Angle":"45","BaseKnockBackSetKnockback":"30","LandingLag":null,"AutoCancel":null,"KnockbackGrowth":"90","MoveType":"special","IsWeightDependent":false,"Game":"Smash4","Related":{"Smash4":{"Character":"http://api.kuroganehammer.com/api/characters/name/PAC-MAN?game=smash4","Self":"http://api.kuroganehammer.com/api/moves/54fd4ceef3fe400abbec5a1e346649b1?game=smash4"},"Ultimate":{"Character":"http://api.kuroganehammer.com/api/characters/name/PAC-MAN?game=ultimate"}},"Links":[{"Rel":"self","Href":"http://api.kuroganehammer.com/api/moves/54fd4ceef3fe400abbec5a1e346649b1?game=smash4"},{"Rel":"character","Href":"http://api.kuroganehammer.com/api/characters/name/PAC-MAN?game=smash4"}]},{"InstanceId":"efab4f19abbd42fba9c31f28e45cd714","Name":"Fire Hydrant (Horizontal Water)","OwnerId":38,"Owner":"PAC-MAN","HitboxActive":"1- (Unblockable)","FirstActionableFrame":"-","BaseDamage":"0","Angle":"361","BaseKnockBackSetKnockback":"W: 45","LandingLag":null,"AutoCancel":null,"KnockbackGrowth":"135","MoveType":"special","IsWeightDependent":false,"Game":"Smash4","Related":{"Smash4":{"Character":"http://api.kuroganehammer.com/api/characters/name/PAC-MAN?game=smash4","Self":"http://api.kuroganehammer.com/api/moves/efab4f19abbd42fba9c31f28e45cd714?game=smash4"},"Ultimate":{"Character":"http://api.kuroganehammer.com/api/characters/name/PAC-MAN?game=ultimate"}},"Links":[{"Rel":"self","Href":"http://api.kuroganehammer.com/api/moves/efab4f19abbd42fba9c31f28e45cd714?game=smash4"},{"Rel":"character","Href":"http://api.kuroganehammer.com/api/characters/name/PAC-MAN?game=smash4"}]},{"InstanceId":"f275405cac6a4ab5bd534bcae7de3009","Name":"Fire Hydrant (Vertical Water)","OwnerId":38,"Owner":"PAC-MAN","HitboxActive":"1- (Unblockable)","FirstActionableFrame":"-","BaseDamage":"0","Angle":"90","BaseKnockBackSetKnockback":"W: 45","LandingLag":null,"AutoCancel":null,"KnockbackGrowth":"135","MoveType":"special","IsWeightDependent":false,"Game":"Smash4","Related":{"Smash4":{"Character":"http://api.kuroganehammer.com/api/characters/name/PAC-MAN?game=smash4","Self":"http://api.kuroganehammer.com/api/moves/f275405cac6a4ab5bd534bcae7de3009?game=smash4"},"Ultimate":{"Character":"http://api.kuroganehammer.com/api/characters/name/PAC-MAN?game=ultimate"}},"Links":[{"Rel":"self","Href":"http://api.kuroganehammer.com/api/moves/f275405cac6a4ab5bd534bcae7de3009?game=smash4"},{"Rel":"character","Href":"http://api.kuroganehammer.com/api/characters/name/PAC-MAN?game=smash4"}]},{"InstanceId":"e60790a7a83243279a04103d134057eb","Name":"Fthrow","OwnerId":38,"Owner":"PAC-MAN","HitboxActive":null,"FirstActionableFrame":null,"BaseDamage":"6","Angle":"58","BaseKnockBackSetKnockback":"48","LandingLag":null,"AutoCancel":null,"KnockbackGrowth":"65","MoveType":"throw","IsWeightDependent":true,"Game":"Smash4","Related":{"Smash4":{"Character":"http://api.kuroganehammer.com/api/characters/name/PAC-MAN?game=smash4","Self":"http://api.kuroganehammer.com/api/moves/e60790a7a83243279a04103d134057eb?game=smash4"},"Ultimate":{"Character":"http://api.kuroganehammer.com/api/characters/name/PAC-MAN?game=ultimate"}},"Links":[{"Rel":"self","Href":"http://api.kuroganehammer.com/api/moves/e60790a7a83243279a04103d134057eb?game=smash4"},{"Rel":"character","Href":"http://api.kuroganehammer.com/api/characters/name/PAC-MAN?game=smash4"}]},{"InstanceId":"d41e3517c2564644becbc11c968b1418","Name":"Bthrow","OwnerId":38,"Owner":"PAC-MAN","HitboxActive":null,"FirstActionableFrame":null,"BaseDamage":"11","Angle":"45","BaseKnockBackSetKnockback":"70","LandingLag":null,"AutoCancel":null,"KnockbackGrowth":"61","MoveType":"throw","IsWeightDependent":true,"Game":"Smash4","Related":{"Smash4":{"Character":"http://api.kuroganehammer.com/api/characters/name/PAC-MAN?game=smash4","Self":"http://api.kuroganehammer.com/api/moves/d41e3517c2564644becbc11c968b1418?game=smash4"},"Ultimate":{"Character":"http://api.kuroganehammer.com/api/characters/name/PAC-MAN?game=ultimate"}},"Links":[{"Rel":"self","Href":"http://api.kuroganehammer.com/api/moves/d41e3517c2564644becbc11c968b1418?game=smash4"},{"Rel":"character","Href":"http://api.kuroganehammer.com/api/characters/name/PAC-MAN?game=smash4"}]},{"InstanceId":"c273849acf9542ec9d5b5f873b20f9c3","Name":"Uthrow","OwnerId":38,"Owner":"PAC-MAN","HitboxActive":null,"FirstActionableFrame":null,"BaseDamage":"5","Angle":"89","BaseKnockBackSetKnockback":"60","LandingLag":null,"AutoCancel":null,"KnockbackGrowth":"100","MoveType":"throw","IsWeightDependent":true,"Game":"Smash4","Related":{"Smash4":{"Character":"http://api.kuroganehammer.com/api/characters/name/PAC-MAN?game=smash4","Self":"http://api.kuroganehammer.com/api/moves/c273849acf9542ec9d5b5f873b20f9c3?game=smash4"},"Ultimate":{"Character":"http://api.kuroganehammer.com/api/characters/name/PAC-MAN?game=ultimate"}},"Links":[{"Rel":"self","Href":"http://api.kuroganehammer.com/api/moves/c273849acf9542ec9d5b5f873b20f9c3?game=smash4"},{"Rel":"character","Href":"http://api.kuroganehammer.com/api/characters/name/PAC-MAN?game=smash4"}]},{"InstanceId":"e735b39a6db24be88addb62042bcfee5","Name":"Dthrow","OwnerId":38,"Owner":"PAC-MAN","HitboxActive":null,"FirstActionableFrame":null,"BaseDamage":"1.5&#37;&#215;3, 6","Angle":"45","BaseKnockBackSetKnockback":"60","LandingLag":null,"AutoCancel":null,"KnockbackGrowth":"55","MoveType":"throw","IsWeightDependent":false,"Game":"Smash4","Related":{"Smash4":{"Character":"http://api.kuroganehammer.com/api/characters/name/PAC-MAN?game=smash4","Self":"http://api.kuroganehammer.com/api/moves/e735b39a6db24be88addb62042bcfee5?game=smash4"},"Ultimate":{"Character":"http://api.kuroganehammer.com/api/characters/name/PAC-MAN?game=ultimate"}},"Links":[{"Rel":"self","Href":"http://api.kuroganehammer.com/api/moves/e735b39a6db24be88addb62042bcfee5?game=smash4"},{"Rel":"character","Href":"http://api.kuroganehammer.com/api/characters/name/PAC-MAN?game=smash4"}]}]