[{"InstanceId":"42bb52359f1340a38a3974db6e867d99","Name":"AirAcceleration","OwnerId":54,"Owner":"Wario","Values":[{"Value":"0.08","Owner":"Wario","OwnerId":54,"Name":"MAX ADDITIONAL"},{"Value":"0.04","Owner":"Wario","OwnerId":54,"Name":"BASE VALUE"},{"Value":"0.12","Owner":"Wario","OwnerId":54,"Name":"TOTAL"}],"Game":"Ultimate","Related":{"Smash4":{"Character":"http://api.kuroganehammer.com/api/characters/name/Wario?game=smash4"},"Ultimate":{"Character":"http://api.kuroganehammer.com/api/characters/name/Wario?game=ultimate","Self":"http://api.kuroganehammer.com/api/characterattributes/42bb52359f1340a38a3974db6e867d99?game=ultimate"}},"Links":[{"Rel":"self","Href":"http://api.kuroganehammer.com/api/characterattributes/42bb52359f1340a38a3974db6e867d99?game=ultimate"},{"Rel":"character","Href":"http://api.kuroganehammer.com/api/characters/name/Wario?game=ultimate"}]},{"InstanceId":"25d9a64072b14d66a1c91237d107d14f","Name":"AirSpeed","OwnerId":54,"Owner":"Wario","Values":[{"Value":"1.271","Owner":"Wario","OwnerId":54,"Name":"MAX AIR SPEED VALUE"}],"Game":"Ultimate","Related":{"Smash4":{"Character":"http://api.kuroganehammer.com/api/characters/name/Wario?game=smash4"},"Ultimate":{"Character":"http://api.kuroganehammer.com/api/characters/name/Wario?game=ultimate","Self":"http://api.kuroganehammer.com/api/characterattributes/25d9a64072b14d66a1c91237d107d14f?game=ultimate"}},"Links":[{"Rel":"self","Href":"http://api.kuroganehammer.com/api/characterattributes/25d9a64072b14d66a1c91237d107d14f?game=ultimate"},{"Rel":"character","Href":"http://api.kuroganehammer.com/api/characters/name/Wario?game=ultimate"}]},{"InstanceId":"0a97d6f72c904fdbb20de7745efd6df7","Name":"FallSpeed","OwnerId":54,"Owner":"Wario","Values":[{"Value":"1.61","Owner":"Wario","OwnerId":54,"Name":"MAX FALL SPEED"},{"Value":"2.576","Owner":"Wario","OwnerId":54,"Name":"FAST FALL SPEED"},{"Value":"60%","Owner":"Wario","OwnerId":54,"Name":"SPEED INCREASE"}],"Game":"Ultimate","Related":{"Smash4":{"Character":"http://api.kuroganehammer.com/api/characters/name/Wario?game=smash4"},"Ultimate":{"Character":"http://api.kuroganehammer.com/api/characters/name/Wario?game=ultimate","Self":"http://api.kuroganehammer.com/api/characterattributes/0a97d6f72c904fdbb20de7745efd6df7?game=ultimate"}},"Links":[{"Rel":"self","Href":"http://api.kuroganehammer.com/api/characterattributes/0a97d6f72c904fdbb20de7745efd6df7?game=ultimate"},{"Rel":"character","Href":"http://api.kuroganehammer.com/api/characters/name/Wario?game=ultimate"}]},{"InstanceId":"7f2ea937086641cfaef8961122fc28ec","Name":"RunSpeed","OwnerId":54,"Owner":"Wario","Values":[{"Value":"1.837","Owner":"Wario","OwnerId":54,"Name":"INITIAL DASH VALUE"}],"Game":"Ultimate","Related":{"Smash4":{"Character":"http://api.kuroganehammer.com/api/characters/name/Wario?game=smash4"},"Ultimate":{"Character":"http://api.kuroganehammer.com/api/characters/name/Wario?game=ultimate","Self":"http://api.kuroganehammer.com/api/characterattributes/7f2ea937086641cfaef8961122fc28ec?game=ultimate"}},"Links":[{"Rel":"self","Href":"http://api.kuroganehammer.com/api/characterattributes/7f2ea937086641cfaef8961122fc28ec?game=ultimate"},{"Rel":"character","Href":"http://api.kuroganehammer.com/api/characters/name/Wario?game=ultimate"}]},{"InstanceId":"00543f8631a046928bac5b605367be80","Name":"WalkSpeed","OwnerId":54,"Owner":"Wario","Values":[{"Value":"0.889","Owner":"Wario","OwnerId":54,"Name":"MAX WALK SPEED VALUE"}],"Game":"Ultimate","Related":{"Smash4":{"Character":"http://api.kuroganehammer.com/api/characters/name/Wario?game=smash4"},"Ultimate":{"Character":"http://api.kuroganehammer.com/api/characters/name/Wario?game=ultimate","Self":"http://api.kuroganehammer.com/api/characterattributes/00543f8631a046928bac5b605367be80?game=ultimate"}},"Links":[{"Rel":"self","Href":"http://api.kuroganehammer.com/api/characterattributes/00543f8631a046928bac5b605367be80?game=ultimate"},{"Rel":"character","Href":"http://api.kuroganehammer.com/api/characters/name/Wario?game=ultimate"}]},{"InstanceId":"c9a8bd52c0274336aefce110fa6f5e51","Name":"Weight","OwnerId":54,"Owner":"Wario","Values":[{"Value":"107","Owner":"Wario","OwnerId":54,"Name":"WEIGHT VALUE"}],"Game":"Ultimate","Related":{"Smash4":{"Character":"http://api.kuroganehammer.com/api/characters/name/Wario?game=smash4"},"Ultimate":{"Character":"http://api.kuroganehammer.com/api/characters/name/Wario?game=ultimate","Self":"http://api.kuroganehammer.com/api/characterattributes/c9a8bd52c0274336aefce110fa6f5e51?game=ultimate"}},"Links":[{"Rel":"self","Href":"http://api.kuroganehammer.com/api/characterattributes/c9a8bd52c0274336aefce110fa6f5e51?game=ultimate"},{"Rel":"character","Href":"http://api.kuroganehammer.com/api/characters/name/Wario?game=ultimate"}]}]